{"location":[],"has_floor":1,"is_new_url":0,"forum":{"id":2432903,"name":"minecraft","is_exists":1,"avatar":"http:\/\/imgsrc.baidu.com\/forum\/pic\/item\/9922720e0cf3d7cafaf3b171f71fbe096b63a9b4.jpg"},"add_post":{"last_addition_content":"\u5582\u718a","last_addition_time":"","post_id":22616303153,"create_time":1343886776,"already_count":0,"total_count":10,"warn_msg":"\u5427\u7b49\u7ea71\u7ea7\u4e4b\u4e0a\u53ef\u4ee5\u4f7f\u7528\u8ffd\u52a0\u529f\u80fd"},"user":{"is_login":0,"id":"","name":"","name_show":"","portrait":"","type":"","level_id":"","is_like":"","is_manager":"","bimg_url":"","pay_member_info":"","ios_bimg_format":"","bimg_end_time":"","is_mem":"","is_select_tail":""},"anti":{"tbs":"115000b858ad98971469774678","ifvoice":1,"voice_message":"\u54ce\u5440\uff0c\u4e09\u7ea7\u4ee5\u4e0a\u624d\u80fd\u53d1\u8bed\u97f3\uff0c\u901f\u901f\u5347\u7ea7\u5427","video_message":"","ifaddition":0,"forbid_flag":1,"forbid_info":"\u672c\u5427\u76ee\u524d\u4ec5\u9650\u767b\u5f55\u7528\u6237\u53d1\u8d34","ifpost":0,"ifposta":0,"ifxiaoying":""},"page":{"req_num":30,"page_size":30,"offset":6360,"current_page":213,"total_page":301,"total_num":9030,"pnum":0,"tnum":0,"has_more":1,"has_prev":1},"post_list":[{"id":"30941245238","title":"\u56de\u590d\uff1a\u76f4\u64ad\uff0cMC 1.3 \u539f\u7248\u751f\u5b58","floor":14764,"time":1364695675,"content":[{"type":0,"text":"\u7ee7\u7eed\u5237\uff0c\u4ecd\u7136\u662f\u4ece\u7a00\u6709\u7684\u5199\u4e66\u4ea4\u6613\u5f00\u59cb\u5237\u8d77\n\u8fd9\u4e2a\u4ea4\u6613\u7684\u6982\u7387\u662f7%\nPS \u6982\u7387\u53ef\u4ee5\u4ecewiki\u4e0a\u67e5\n\u5f53\u7136\u4e5f\u53ef\u4ee5\u81ea\u5df1\u770b\u6e90\u7801\u7136\u540e\u7b97\u51fa\u6765\n \n\u2014\u2014\u6765\u81ea MCLive"},{"type":3,"src":"http:\/\/imgsrc.baidu.com\/forum\/pic\/item\/5dab6fed2e738bd4e56f8851a08b87d6277ff927.jpg","bsize":"560,314","size":null}],"lbs_info":[],"is_vote":0,"ptype":null,"is_voice":0,"arr_video":[],"bimg_url":"","ios_bimg_format":"","is_bub":0,"has_signature":0,"pb_live":null,"signature":[],"vote_id":0,"tail_info":[],"author":{"id":105525655,"name":"defanive2","name_show":"defanive2","portrait":"9731646566616e697665324a06","type":1,"is_like":1,"level_id":14,"level_name":"\u65e0\u5c3d\u9ed1\u591c","is_interestman":"","iconinfo":[],"fans_nickname":"","is_mem":0,"tb_vip":[],"is_bawu":0,"bawu_type":"","tshow_icon":[],"new_tshow_icon":[]},"sub_post_number":6,"add_post_number":0,"sub_post_list":[],"add_post_list":[]},{"id":"30941268218","title":"\u56de\u590d\uff1a\u76f4\u64ad\uff0cMC 1.3 \u539f\u7248\u751f\u5b58","floor":14765,"time":1364695722,"content":[{"type":0,"text":"RP\u771f\u4e0d\u9519\uff0c\u8fd8\u5f97\u518d\u5237\u4e00\u6b21\n \n\u2014\u2014\u6765\u81ea MCLive"},{"type":3,"src":"http:\/\/imgsrc.baidu.com\/forum\/pic\/item\/48e33b178a82b901020ef953728da9773812efca.jpg","bsize":"560,314","size":null}],"lbs_info":[],"is_vote":0,"ptype":null,"is_voice":0,"arr_video":[],"bimg_url":"","ios_bimg_format":"","is_bub":0,"has_signature":0,"pb_live":null,"signature":[],"vote_id":0,"tail_info":[],"author":{"id":105525655,"name":"defanive2","name_show":"defanive2","portrait":"9731646566616e697665324a06","type":1,"is_like":1,"level_id":14,"level_name":"\u65e0\u5c3d\u9ed1\u591c","is_interestman":"","iconinfo":[],"fans_nickname":"","is_mem":0,"tb_vip":[],"is_bawu":0,"bawu_type":"","tshow_icon":[],"new_tshow_icon":[]},"sub_post_number":9,"add_post_number":0,"sub_post_list":[],"add_post_list":[]},{"id":"30941295698","title":"\u56de\u590d\uff1a\u76f4\u64ad\uff0cMC 1.3 \u539f\u7248\u751f\u5b58","floor":14766,"time":1364695778,"content":[{"type":0,"text":"\u7b2c\u4e8c\u9879\u4ea4\u6613\uff0c\u4e66\n\u4e0d\u7b97\u5dee\uff0c\u867d\u7136\u4e0d\u662f\u7a00\u6709\u4ea4\u6613\n \n\u2014\u2014\u6765\u81ea MCLive"},{"type":3,"src":"http:\/\/imgsrc.baidu.com\/forum\/pic\/item\/1015154e251f95ca2c1ca8d6c8177f3e66095280.jpg","bsize":"560,314","size":null}],"lbs_info":[],"is_vote":0,"ptype":null,"is_voice":0,"arr_video":[],"bimg_url":"","ios_bimg_format":"","is_bub":0,"has_signature":0,"pb_live":null,"signature":[],"vote_id":0,"tail_info":[],"author":{"id":105525655,"name":"defanive2","name_show":"defanive2","portrait":"9731646566616e697665324a06","type":1,"is_like":1,"level_id":14,"level_name":"\u65e0\u5c3d\u9ed1\u591c","is_interestman":"","iconinfo":[],"fans_nickname":"","is_mem":0,"tb_vip":[],"is_bawu":0,"bawu_type":"","tshow_icon":[],"new_tshow_icon":[]},"sub_post_number":6,"add_post_number":0,"sub_post_list":[],"add_post_list":[]},{"id":"30941318039","title":"\u56de\u590d\uff1a\u76f4\u64ad\uff0cMC 1.3 \u539f\u7248\u751f\u5b58","floor":14767,"time":1364695822,"content":[{"type":0,"text":"\u4e66\u67b6\uff0c\u4e5f\u662f\u5e38\u89c1\u4ea4\u6613\n\u770b\u8d77\u6765\u4ee5\u540e\u8981\u5237\u51fa\u7a00\u6709\u4ea4\u6613\u96be\u5ea6\u5c31\u9ad8\u4e86\n \n\u2014\u2014\u6765\u81ea MCLive"},{"type":3,"src":"http:\/\/imgsrc.baidu.com\/forum\/pic\/item\/e746002dd42a2834ac690c6b5ab5c9ea14cebfa6.jpg","bsize":"560,314","size":null}],"lbs_info":[],"is_vote":0,"ptype":null,"is_voice":0,"arr_video":[],"bimg_url":"","ios_bimg_format":"","is_bub":0,"has_signature":0,"pb_live":null,"signature":[],"vote_id":0,"tail_info":[],"author":{"id":105525655,"name":"defanive2","name_show":"defanive2","portrait":"9731646566616e697665324a06","type":1,"is_like":1,"level_id":14,"level_name":"\u65e0\u5c3d\u9ed1\u591c","is_interestman":"","iconinfo":[],"fans_nickname":"","is_mem":0,"tb_vip":[],"is_bawu":0,"bawu_type":"","tshow_icon":[],"new_tshow_icon":[]},"sub_post_number":5,"add_post_number":0,"sub_post_list":[],"add_post_list":[]},{"id":"30941329754","title":"\u56de\u590d\uff1a\u76f4\u64ad\uff0cMC 1.3 \u539f\u7248\u751f\u5b58","floor":14768,"time":1364695846,"content":[{"type":0,"text":"\u6ca1\u6709\u66f4\u65b0\u4ea4\u6613\u9879\u76ee\uff0c\u518d\u5237\u4e00\u6b21\n \n\u2014\u2014\u6765\u81ea MCLive"},{"type":3,"src":"http:\/\/imgsrc.baidu.com\/forum\/pic\/item\/1a09d8faaf51f3de61b89c0495eef01f3a297963.jpg","bsize":"560,314","size":null}],"lbs_info":[],"is_vote":0,"ptype":null,"is_voice":0,"arr_video":[],"bimg_url":"","ios_bimg_format":"","is_bub":0,"has_signature":0,"pb_live":null,"signature":[],"vote_id":0,"tail_info":[],"author":{"id":105525655,"name":"defanive2","name_show":"defanive2","portrait":"9731646566616e697665324a06","type":1,"is_like":1,"level_id":14,"level_name":"\u65e0\u5c3d\u9ed1\u591c","is_interestman":"","iconinfo":[],"fans_nickname":"","is_mem":0,"tb_vip":[],"is_bawu":0,"bawu_type":"","tshow_icon":[],"new_tshow_icon":[]},"sub_post_number":5,"add_post_number":0,"sub_post_list":[],"add_post_list":[]},{"id":"30941337431","title":"\u56de\u590d\uff1a\u76f4\u64ad\uff0cMC 1.3 \u539f\u7248\u751f\u5b58","floor":14769,"time":1364695861,"content":[{"type":0,"text":"\u8fd8\u662f\u6ca1\u6709\u66f4\u65b0\uff0c\u518d\u5237\u4e00\u6b21\n \n\u2014\u2014\u6765\u81ea MCLive"},{"type":3,"src":"http:\/\/imgsrc.baidu.com\/forum\/pic\/item\/3f868c014c086e06796c052b03087bf40bd1cbad.jpg","bsize":"560,314","size":null}],"lbs_info":[],"is_vote":0,"ptype":null,"is_voice":0,"arr_video":[],"bimg_url":"","ios_bimg_format":"","is_bub":0,"has_signature":0,"pb_live":null,"signature":[],"vote_id":0,"tail_info":[],"author":{"id":105525655,"name":"defanive2","name_show":"defanive2","portrait":"9731646566616e697665324a06","type":1,"is_like":1,"level_id":14,"level_name":"\u65e0\u5c3d\u9ed1\u591c","is_interestman":"","iconinfo":[],"fans_nickname":"","is_mem":0,"tb_vip":[],"is_bawu":0,"bawu_type":"","tshow_icon":[],"new_tshow_icon":[]},"sub_post_number":8,"add_post_number":0,"sub_post_list":[],"add_post_list":[]},{"id":"30941353208","title":"\u56de\u590d\uff1a\u76f4\u64ad\uff0cMC 1.3 \u539f\u7248\u751f\u5b58","floor":14770,"time":1364695893,"content":[{"type":0,"text":"\u4ecd\u7136\u6ca1\u6709\uff0c\u770b\u8d77\u6765\u6211RP\u5df2\u7ecf\u574f\u6389\u4e86\u4e48\u3002\u3002\n \n\u2014\u2014\u6765\u81ea MCLive"},{"type":3,"src":"http:\/\/imgsrc.baidu.com\/forum\/pic\/item\/b751001f95cad1c85aa5d9477e3e6709c93d5157.jpg","bsize":"560,314","size":null}],"lbs_info":[],"is_vote":0,"ptype":null,"is_voice":0,"arr_video":[],"bimg_url":"","ios_bimg_format":"","is_bub":0,"has_signature":0,"pb_live":null,"signature":[],"vote_id":0,"tail_info":[],"author":{"id":105525655,"name":"defanive2","name_show":"defanive2","portrait":"9731646566616e697665324a06","type":1,"is_like":1,"level_id":14,"level_name":"\u65e0\u5c3d\u9ed1\u591c","is_interestman":"","iconinfo":[],"fans_nickname":"","is_mem":0,"tb_vip":[],"is_bawu":0,"bawu_type":"","tshow_icon":[],"new_tshow_icon":[]},"sub_post_number":19,"add_post_number":0,"sub_post_list":[],"add_post_list":[]},{"id":"30941370089","title":"\u56de\u590d\uff1a\u76f4\u64ad\uff0cMC 1.3 \u539f\u7248\u751f\u5b58","floor":14771,"time":1364695927,"content":[{"type":0,"text":"\u7ec8\u4e8e\u3002\u3002\u6307\u5357\u9488\uff0c\u4e0d\u9519\n\u53bb\u6362\u70b9\u7eff\u5b9d\u77f3\u7528\n \n\u2014\u2014\u6765\u81ea MCLive"},{"type":3,"src":"http:\/\/imgsrc.baidu.com\/forum\/pic\/item\/8b2ca244ebf81a4cc162c9a9d62a6059252da619.jpg","bsize":"560,314","size":null}],"lbs_info":[],"is_vote":0,"ptype":null,"is_voice":0,"arr_video":[],"bimg_url":"","ios_bimg_format":"","is_bub":0,"has_signature":0,"pb_live":null,"signature":[],"vote_id":0,"tail_info":[],"author":{"id":105525655,"name":"defanive2","name_show":"defanive2","portrait":"9731646566616e697665324a06","type":1,"is_like":1,"level_id":14,"level_name":"\u65e0\u5c3d\u9ed1\u591c","is_interestman":"","iconinfo":[],"fans_nickname":"","is_mem":0,"tb_vip":[],"is_bawu":0,"bawu_type":"","tshow_icon":[],"new_tshow_icon":[]},"sub_post_number":6,"add_post_number":0,"sub_post_list":[],"add_post_list":[]},{"id":"30941391484","title":"\u56de\u590d\uff1a\u76f4\u64ad\uff0cMC 1.3 \u539f\u7248\u751f\u5b58","floor":14772,"time":1364695970,"content":[{"type":0,"text":"\u8bf4\u5230\u7518\u8517\u7684\u50a8\u91cf\uff0c\u4e00\u7bb1\u5df2\u7ecf\u7528\u5b8c\u4e86\n\u73b0\u5728\u8fd8\u6709\u8fd12\u7bb1\u7684\u50a8\u91cf\n\u5e94\u8be5\u8fd8\u591f\u7528\u5f88\u4e45\n \n\u2014\u2014\u6765\u81ea MCLive"},{"type":3,"src":"http:\/\/imgsrc.baidu.com\/forum\/pic\/item\/e5cfd203918fa0ec7b8c416d279759ee3d6ddb22.jpg","bsize":"560,314","size":null}],"lbs_info":[],"is_vote":0,"ptype":null,"is_voice":0,"arr_video":[],"bimg_url":"","ios_bimg_format":"","is_bub":0,"has_signature":0,"pb_live":null,"signature":[],"vote_id":0,"tail_info":[],"author":{"id":105525655,"name":"defanive2","name_show":"defanive2","portrait":"9731646566616e697665324a06","type":1,"is_like":1,"level_id":14,"level_name":"\u65e0\u5c3d\u9ed1\u591c","is_interestman":"","iconinfo":[],"fans_nickname":"","is_mem":0,"tb_vip":[],"is_bawu":0,"bawu_type":"","tshow_icon":[],"new_tshow_icon":[]},"sub_post_number":8,"add_post_number":0,"sub_post_list":[],"add_post_list":[]},{"id":"30941474106","title":"\u56de\u590d\uff1a\u76f4\u64ad\uff0cMC 1.3 \u539f\u7248\u751f\u5b58","floor":14773,"time":1364696134,"content":[{"type":0,"text":"\u6765\u6362\u6307\u5357\u9488\n \n\u2014\u2014\u6765\u81ea MCLive"},{"type":3,"src":"http:\/\/imgsrc.baidu.com\/forum\/pic\/item\/7cf28e64034f78f0ce1cbe9378310a55b3191c5d.jpg","bsize":"560,314","size":null}],"lbs_info":[],"is_vote":0,"ptype":null,"is_voice":0,"arr_video":[],"bimg_url":"","ios_bimg_format":"","is_bub":0,"has_signature":0,"pb_live":null,"signature":[],"vote_id":0,"tail_info":[],"author":{"id":105525655,"name":"defanive2","name_show":"defanive2","portrait":"9731646566616e697665324a06","type":1,"is_like":1,"level_id":14,"level_name":"\u65e0\u5c3d\u9ed1\u591c","is_interestman":"","iconinfo":[],"fans_nickname":"","is_mem":0,"tb_vip":[],"is_bawu":0,"bawu_type":"","tshow_icon":[],"new_tshow_icon":[]},"sub_post_number":6,"add_post_number":0,"sub_post_list":[],"add_post_list":[]},{"id":"30941499901","title":"\u56de\u590d\uff1a\u76f4\u64ad\uff0cMC 1.3 \u539f\u7248\u751f\u5b58","floor":14774,"time":1364696185,"content":[{"type":0,"text":"\u4e0d\u9519\uff0c\u949f\uff01\n\u63a5\u4e0b\u6765\u8fd8\u6709 \u73bb\u7483 \u9700\u8981\u5237\u4e86\n\u9700\u8981RP\uff01\n \n\u2014\u2014\u6765\u81ea MCLive"},{"type":3,"src":"http:\/\/imgsrc.baidu.com\/forum\/pic\/item\/cc2989af2edda3ccc7f99c4000e93901213f9254.jpg","bsize":"560,314","size":null}],"lbs_info":[],"is_vote":0,"ptype":null,"is_voice":0,"arr_video":[],"bimg_url":"","ios_bimg_format":"","is_bub":0,"has_signature":0,"pb_live":null,"signature":[],"vote_id":0,"tail_info":[],"author":{"id":105525655,"name":"defanive2","name_show":"defanive2","portrait":"9731646566616e697665324a06","type":1,"is_like":1,"level_id":14,"level_name":"\u65e0\u5c3d\u9ed1\u591c","is_interestman":"","iconinfo":[],"fans_nickname":"","is_mem":0,"tb_vip":[],"is_bawu":0,"bawu_type":"","tshow_icon":[],"new_tshow_icon":[]},"sub_post_number":14,"add_post_number":0,"sub_post_list":[],"add_post_list":[]},{"id":"30941537240","title":"\u56de\u590d\uff1a\u76f4\u64ad\uff0cMC 1.3 \u539f\u7248\u751f\u5b58","floor":14775,"time":1364696259,"content":[{"type":0,"text":"\u6765\u6765\u6765\uff0c\u6c42RP\uff0c\u8d76\u5feb\u51fa\u73bb\u7483\u5427\n \n\u2014\u2014\u6765\u81ea MCLive"},{"type":3,"src":"http:\/\/imgsrc.baidu.com\/forum\/pic\/item\/f5946210b912c8fccf8cd2adfd039245d6882175.jpg","bsize":"560,314","size":null}],"lbs_info":[],"is_vote":0,"ptype":null,"is_voice":0,"arr_video":[],"bimg_url":"","ios_bimg_format":"","is_bub":0,"has_signature":0,"pb_live":null,"signature":[],"vote_id":0,"tail_info":[],"author":{"id":105525655,"name":"defanive2","name_show":"defanive2","portrait":"9731646566616e697665324a06","type":1,"is_like":1,"level_id":14,"level_name":"\u65e0\u5c3d\u9ed1\u591c","is_interestman":"","iconinfo":[],"fans_nickname":"","is_mem":0,"tb_vip":[],"is_bawu":0,"bawu_type":"","tshow_icon":[],"new_tshow_icon":[]},"sub_post_number":7,"add_post_number":0,"sub_post_list":[],"add_post_list":[]},{"id":"30941544576","title":"\u56de\u590d\uff1a\u76f4\u64ad\uff0cMC 1.3 \u539f\u7248\u751f\u5b58","floor":14776,"time":1364696273,"content":[{"type":0,"text":"\u7ed3\u679c\u6ca1\u51fa\uff0c\u8fd8\u8981\u7ee7\u7eed\u5237\n \n\u2014\u2014\u6765\u81ea MCLive"},{"type":3,"src":"http:\/\/imgsrc.baidu.com\/forum\/pic\/item\/0a0f24e93901213f787b6abc55e736d12f2e9521.jpg","bsize":"560,314","size":null}],"lbs_info":[],"is_vote":0,"ptype":null,"is_voice":0,"arr_video":[],"bimg_url":"","ios_bimg_format":"","is_bub":0,"has_signature":0,"pb_live":null,"signature":[],"vote_id":0,"tail_info":[],"author":{"id":105525655,"name":"defanive2","name_show":"defanive2","portrait":"9731646566616e697665324a06","type":1,"is_like":1,"level_id":14,"level_name":"\u65e0\u5c3d\u9ed1\u591c","is_interestman":"","iconinfo":[],"fans_nickname":"","is_mem":0,"tb_vip":[],"is_bawu":0,"bawu_type":"","tshow_icon":[],"new_tshow_icon":[]},"sub_post_number":5,"add_post_number":0,"sub_post_list":[],"add_post_list":[]},{"id":"30941603579","title":"\u56de\u590d\uff1a\u76f4\u64ad\uff0cMC 1.3 \u539f\u7248\u751f\u5b58","floor":14778,"time":1364696388,"content":[{"type":0,"text":"\u518d\u6765\uff01\u6c42RP\uff01\n \n\u2014\u2014\u6765\u81ea MCLive"},{"type":3,"src":"http:\/\/imgsrc.baidu.com\/forum\/pic\/item\/fcd42f46f21fbe09e3c6e7746a600c338644add1.jpg","bsize":"560,314","size":null}],"lbs_info":[],"is_vote":0,"ptype":null,"is_voice":0,"arr_video":[],"bimg_url":"","ios_bimg_format":"","is_bub":0,"has_signature":0,"pb_live":null,"signature":[],"vote_id":0,"tail_info":[],"author":{"id":105525655,"name":"defanive2","name_show":"defanive2","portrait":"9731646566616e697665324a06","type":1,"is_like":1,"level_id":14,"level_name":"\u65e0\u5c3d\u9ed1\u591c","is_interestman":"","iconinfo":[],"fans_nickname":"","is_mem":0,"tb_vip":[],"is_bawu":0,"bawu_type":"","tshow_icon":[],"new_tshow_icon":[]},"sub_post_number":11,"add_post_number":0,"sub_post_list":[],"add_post_list":[]},{"id":"30941621589","title":"\u56de\u590d\uff1a\u76f4\u64ad\uff0cMC 1.3 \u539f\u7248\u751f\u5b58","floor":14779,"time":1364696423,"content":[{"type":0,"text":"\u7ed3\u679c\u4ecd\u7136\u5f97\u518d\u5237\u3002\u3002\n \n\u2014\u2014\u6765\u81ea MCLive"},{"type":3,"src":"http:\/\/imgsrc.baidu.com\/forum\/pic\/item\/92d113d3d539b600a7fa28d7e850352ac65cb7bd.jpg","bsize":"560,314","size":null}],"lbs_info":[],"is_vote":0,"ptype":null,"is_voice":0,"arr_video":[],"bimg_url":"","ios_bimg_format":"","is_bub":0,"has_signature":0,"pb_live":null,"signature":[],"vote_id":0,"tail_info":[],"author":{"id":105525655,"name":"defanive2","name_show":"defanive2","portrait":"9731646566616e697665324a06","type":1,"is_like":1,"level_id":14,"level_name":"\u65e0\u5c3d\u9ed1\u591c","is_interestman":"","iconinfo":[],"fans_nickname":"","is_mem":0,"tb_vip":[],"is_bawu":0,"bawu_type":"","tshow_icon":[],"new_tshow_icon":[]},"sub_post_number":5,"add_post_number":0,"sub_post_list":[],"add_post_list":[]},{"id":"30941673844","title":"\u56de\u590d\uff1a\u76f4\u64ad\uff0cMC 1.3 \u539f\u7248\u751f\u5b58","floor":14780,"time":1364696525,"content":[{"type":0,"text":"\u4e2a\u4eba\u5bf9\u8fd9\u4e2a7\u6b21\u5931\u8d25\u54c1\u8fd8\u662f\u5f88\u559c\u6b22\u7684\n\u76ee\u524d\u5df2\u7ecf\u81f3\u5c11\u4ea4\u6613\u4e862\u7ec4\u591a\u7684\u7eff\u5b9d\u77f3\u4e86\n\u6700\u540e\u4e00\u9879\u4ecd\u7136\u662f\u7eb8\n \n\u2014\u2014\u6765\u81ea MCLive"},{"type":3,"src":"http:\/\/imgsrc.baidu.com\/forum\/pic\/item\/fc96bb510fb30f246b95cb63c995d143ad4b0365.jpg","bsize":"560,314","size":null}],"lbs_info":[],"is_vote":0,"ptype":null,"is_voice":0,"arr_video":[],"bimg_url":"","ios_bimg_format":"","is_bub":0,"has_signature":0,"pb_live":null,"signature":[],"vote_id":0,"tail_info":[],"author":{"id":105525655,"name":"defanive2","name_show":"defanive2","portrait":"9731646566616e697665324a06","type":1,"is_like":1,"level_id":14,"level_name":"\u65e0\u5c3d\u9ed1\u591c","is_interestman":"","iconinfo":[],"fans_nickname":"","is_mem":0,"tb_vip":[],"is_bawu":0,"bawu_type":"","tshow_icon":[],"new_tshow_icon":[]},"sub_post_number":11,"add_post_number":0,"sub_post_list":[],"add_post_list":[]},{"id":"30941694103","title":"\u56de\u590d\uff1a\u76f4\u64ad\uff0cMC 1.3 \u539f\u7248\u751f\u5b58","floor":14781,"time":1364696564,"content":[{"type":0,"text":"\u518d\u6765\n \n\u2014\u2014\u6765\u81ea MCLive"},{"type":3,"src":"http:\/\/imgsrc.baidu.com\/forum\/pic\/item\/e016ec3d70cf3bc79d61ea8cd000baa1cd112a0f.jpg","bsize":"560,314","size":null}],"lbs_info":[],"is_vote":0,"ptype":null,"is_voice":0,"arr_video":[],"bimg_url":"","ios_bimg_format":"","is_bub":0,"has_signature":0,"pb_live":null,"signature":[],"vote_id":0,"tail_info":[],"author":{"id":105525655,"name":"defanive2","name_show":"defanive2","portrait":"9731646566616e697665324a06","type":1,"is_like":1,"level_id":14,"level_name":"\u65e0\u5c3d\u9ed1\u591c","is_interestman":"","iconinfo":[],"fans_nickname":"","is_mem":0,"tb_vip":[],"is_bawu":0,"bawu_type":"","tshow_icon":[],"new_tshow_icon":[]},"sub_post_number":5,"add_post_number":0,"sub_post_list":[],"add_post_list":[]},{"id":"30941703664","title":"\u56de\u590d\uff1a\u76f4\u64ad\uff0cMC 1.3 \u539f\u7248\u751f\u5b58","floor":14782,"time":1364696583,"content":[{"type":0,"text":"\u53ef\u60dc\u4ecd\u7136\u6ca1\u6709\uff0c\u8fd8\u53ef\u4ee5\u518d\u6765\u4e00\u6b21\n \n\u2014\u2014\u6765\u81ea MCLive"},{"type":3,"src":"http:\/\/imgsrc.baidu.com\/forum\/pic\/item\/a6209d0e7bec54e7f4ed3d7eb8389b504fc26a68.jpg","bsize":"560,314","size":null}],"lbs_info":[],"is_vote":0,"ptype":null,"is_voice":0,"arr_video":[],"bimg_url":"","ios_bimg_format":"","is_bub":0,"has_signature":0,"pb_live":null,"signature":[],"vote_id":0,"tail_info":[],"author":{"id":105525655,"name":"defanive2","name_show":"defanive2","portrait":"9731646566616e697665324a06","type":1,"is_like":1,"level_id":14,"level_name":"\u65e0\u5c3d\u9ed1\u591c","is_interestman":"","iconinfo":[],"fans_nickname":"","is_mem":0,"tb_vip":[],"is_bawu":0,"bawu_type":"","tshow_icon":[],"new_tshow_icon":[]},"sub_post_number":5,"add_post_number":0,"sub_post_list":[],"add_post_list":[]},{"id":"30941720083","title":"\u56de\u590d\uff1a\u76f4\u64ad\uff0cMC 1.3 \u539f\u7248\u751f\u5b58","floor":14783,"time":1364696615,"content":[{"type":0,"text":"\u7ec8\u4e8e\u51fa\u4e86\uff0c\u5230\u5e95\u662f\u4ec0\u4e48\u5462\uff1f\uff01\n\u5e0c\u671b\u662f\u73bb\u7483\u554a\uff01\uff01\n \n\u2014\u2014\u6765\u81ea MCLive"},{"type":3,"src":"http:\/\/imgsrc.baidu.com\/forum\/pic\/item\/d2e497fb43166d22352d32f4472309f79052d213.jpg","bsize":"560,314","size":null}],"lbs_info":[],"is_vote":0,"ptype":null,"is_voice":0,"arr_video":[],"bimg_url":"","ios_bimg_format":"","is_bub":0,"has_signature":0,"pb_live":null,"signature":[],"vote_id":0,"tail_info":[],"author":{"id":105525655,"name":"defanive2","name_show":"defanive2","portrait":"9731646566616e697665324a06","type":1,"is_like":1,"level_id":14,"level_name":"\u65e0\u5c3d\u9ed1\u591c","is_interestman":"","iconinfo":[],"fans_nickname":"","is_mem":0,"tb_vip":[],"is_bawu":0,"bawu_type":"","tshow_icon":[],"new_tshow_icon":[]},"sub_post_number":5,"add_post_number":0,"sub_post_list":[],"add_post_list":[]},{"id":"30941777998","title":"\u56de\u590d\uff1a\u76f4\u64ad\uff0cMC 1.3 \u539f\u7248\u751f\u5b58","floor":14784,"time":1364696726,"content":[{"type":0,"text":"\u53ef\u60dc\u4e86\uff0c\u662f\u7eb8\n\u4e0d\u8fc7\uff0c\u5bf9\u4e8e\u8fd9\u4e2a\u6751\u6c11\u8fd8\u67093\u4e2a\u53ef\u80fd\u7684\u4ea4\u6613 \u91d1 \u73bb\u7483 \u9644\u9b54\u4e66\n\u603b\u5171\u52a0\u8d77\u6765\u7684\u51e0\u7387\u662f0.2%+5.2%+1%=6.4%\n\u4e5f\u5c31\u662f\u8bf4\uff0c\u6bcf\u6b21\u4ea4\u6613\u7eb8\uff0c\u53ea\u67096.4%\u51e0\u7387\u4f1a\u5bfc\u81f4\u7eb8\u4ea4\u6613\u4e0d\u518d\u6709\u6548\n\u56e0\u6b64\u5bf9\u6bd4\u4e4b\u524d\u76847\u6b21\u5931\u8d25\u54c1\uff0c\u66f4\u52a0\u6709\u7528\n \n\u2014\u2014\u6765\u81ea MCLive"},{"type":3,"src":"http:\/\/imgsrc.baidu.com\/forum\/pic\/item\/265b88345982b2b7615d1ea430adcbef77099bab.jpg","bsize":"560,314","size":null}],"lbs_info":[],"is_vote":0,"ptype":null,"is_voice":0,"arr_video":[],"bimg_url":"","ios_bimg_format":"","is_bub":0,"has_signature":0,"pb_live":null,"signature":[],"vote_id":0,"tail_info":[],"author":{"id":105525655,"name":"defanive2","name_show":"defanive2","portrait":"9731646566616e697665324a06","type":1,"is_like":1,"level_id":14,"level_name":"\u65e0\u5c3d\u9ed1\u591c","is_interestman":"","iconinfo":[],"fans_nickname":"","is_mem":0,"tb_vip":[],"is_bawu":0,"bawu_type":"","tshow_icon":[],"new_tshow_icon":[]},"sub_post_number":11,"add_post_number":0,"sub_post_list":[],"add_post_list":[]},{"id":"30942036535","title":"\u56de\u590d\uff1a\u76f4\u64ad\uff0cMC 1.3 \u539f\u7248\u751f\u5b58","floor":14786,"time":1364697217,"content":[{"type":0,"text":"\u5176\u5b9e\u4e2a\u4eba\u611f\u89c9\u5e94\u8be5\u5df2\u7ecf\u7b97\u662f\u505a\u5230\u65e0\u9650\u7eb8\u4ea4\u6613\u4e86\n\u6bd5\u7adf7.1%\u7684\u6982\u7387\uff0c\u5e94\u8be5\u80fd\u7528\u5f88\u4e45\u4e86\n\u5982\u679c\u574f\u6389\u4e4b\u540e\u518d\u91cd\u65b0\u5237\u8fc7\u5427\n\u800c\u63a5\u4e0b\u6765\u6211\u4eec\u5f00\u59cb\u5237\u4e00\u4e9b\u5176\u4ed6\u4ea4\u6613\u4e86\n\u4e0b\u4e00\u4e2a\u4ea4\u6613\u5c31\u662f \u4e66\u67b6\n\u5982\u679c\u4e66\u67b6\u53ef\u4ee5\u4f5c\u4e3a\u6700\u540e\u4e00\u4e2a\u4ea4\u6613\u7684\u8bdd\n\u90a3\u4e48\u5c31\u53ef\u4ee5\u65e0\u9650\u6362\u4e66\u67b6\uff0c\u800c\u4e66\u67b6\u6253\u7834\u4e4b\u540e\u53ef\u4ee5\u67093\u672c\u4e66\n\u4e5f\u5c31\u662f\u8bf4\u53ef\u4ee5\u65e0\u9650\u7684\u6362\u4e66\u4e86\uff0c\u4e0d\u518d\u9700\u8981\u517b\u6b96\u725b\n\u4e2a\u4eba\u611f\u89c9\u662f\u5f88\u6709\u5438\u5f15\u529b\u7684\n\u800c\u8fd9\u4e00\u4e2a\u5931\u8d25\u54c1\u5df2\u6709\u7684\u4ea4\u6613\u662f \u5199\u4e66\u3001\u6307\u5357\u9488\u3001\u949f\u3001\u73bb\u7483\u3001\u7eb8\n\u8fd8\u5269 \u4e66\u67b6\u3001\u4e66\n\u56e0\u6b64\u6211\u4eec\u53ef\u4ee5\u8003\u8651\u628a\u8fd9\u4e2a\u7684\u4ea4\u6613\u7ed9\u5237\u6210\u6700\u540e\u4e00\u4e2a\u662f\u4e66\u67b6\n \n\u2014\u2014\u6765\u81ea MCLive"},{"type":3,"src":"http:\/\/imgsrc.baidu.com\/forum\/pic\/item\/0aaeee13495409233cd3421e9358d109b3de4933.jpg","bsize":"560,314","size":null}],"lbs_info":[],"is_vote":0,"ptype":null,"is_voice":0,"arr_video":[],"bimg_url":"","ios_bimg_format":"","is_bub":0,"has_signature":0,"pb_live":null,"signature":[],"vote_id":0,"tail_info":[],"author":{"id":105525655,"name":"defanive2","name_show":"defanive2","portrait":"9731646566616e697665324a06","type":1,"is_like":1,"level_id":14,"level_name":"\u65e0\u5c3d\u9ed1\u591c","is_interestman":"","iconinfo":[],"fans_nickname":"","is_mem":0,"tb_vip":[],"is_bawu":0,"bawu_type":"","tshow_icon":[],"new_tshow_icon":[]},"sub_post_number":5,"add_post_number":0,"sub_post_list":[],"add_post_list":[]},{"id":"30942095762","title":"\u56de\u590d\uff1a\u76f4\u64ad\uff0cMC 1.3 \u539f\u7248\u751f\u5b58","floor":14787,"time":1364697328,"content":[{"type":0,"text":"\u7ed3\u679c\u676f\u5177\u4e86\uff0c\u4e0b\u4e00\u6b65\u5c31\u51fa\u4e86\u4e66\u67b6\n\u4e0d\u8fc7\u73b0\u5728\u53ea\u670925%\u7684\u51e0\u7387\u4f1a\u4f7f\u8fd9\u4e2a\u65e0\u9650\u4ea4\u6613\u6d88\u5931\n\u56e0\u6b64\u4e2a\u4eba\u611f\u89c9\u8fd8\u662f\u53ef\u4ee5\u7528\u5f88\u4e45\u7684\n \n\u2014\u2014\u6765\u81ea MCLive"},{"type":3,"src":"http:\/\/imgsrc.baidu.com\/forum\/pic\/item\/44e2d9039245d688dacd93c4a5c27d1ed31b24a5.jpg","bsize":"560,314","size":null}],"lbs_info":[],"is_vote":0,"ptype":null,"is_voice":0,"arr_video":[],"bimg_url":"","ios_bimg_format":"","is_bub":0,"has_signature":0,"pb_live":null,"signature":[],"vote_id":0,"tail_info":[],"author":{"id":105525655,"name":"defanive2","name_show":"defanive2","portrait":"9731646566616e697665324a06","type":1,"is_like":1,"level_id":14,"level_name":"\u65e0\u5c3d\u9ed1\u591c","is_interestman":"","iconinfo":[],"fans_nickname":"","is_mem":0,"tb_vip":[],"is_bawu":0,"bawu_type":"","tshow_icon":[],"new_tshow_icon":[]},"sub_post_number":7,"add_post_number":0,"sub_post_list":[],"add_post_list":[]},{"id":"30942554988","title":"\u56de\u590d\uff1a\u76f4\u64ad\uff0cMC 1.3 \u539f\u7248\u751f\u5b58","floor":14792,"time":1364698183,"content":[{"type":0,"text":"\u6700\u540e\u628a\u6ca1\u7528\u7684\u6751\u6c11\u90fd\u6e05\u7406\u6389\n\u8fd9\u4e2a\u5de5\u7a0b\u611f\u89c9\u5c31\u5b8c\u6210\u5f97\u5dee\u4e0d\u591a\u4e86\n2\u4e2a\u6751\u6c11\u90fd\u53ef\u4ee5\u8fd1\u4e4e\u65e0\u9650\u5236\u7684\u6362\u7eb8\n\u53e6\u59161\u4e2a\u6751\u6c11\u53ef\u4ee5\u6362\u4e66\u67b6\n\u611f\u89c9\u5e94\u8be5\u5f88\u4e0d\u9519\u4e86\n\u4f11\u606f\u4e00\u4e0b = =\n \n\u2014\u2014\u6765\u81ea MCLive"},{"type":3,"src":"http:\/\/imgsrc.baidu.com\/forum\/pic\/item\/d45cdef2b211931312b9ddd064380cd790238df3.jpg","bsize":"560,314","size":null}],"lbs_info":[],"is_vote":0,"ptype":null,"is_voice":0,"arr_video":[],"bimg_url":"","ios_bimg_format":"","is_bub":0,"has_signature":0,"pb_live":null,"signature":[],"vote_id":0,"tail_info":[],"author":{"id":105525655,"name":"defanive2","name_show":"defanive2","portrait":"9731646566616e697665324a06","type":1,"is_like":1,"level_id":14,"level_name":"\u65e0\u5c3d\u9ed1\u591c","is_interestman":"","iconinfo":[],"fans_nickname":"","is_mem":0,"tb_vip":[],"is_bawu":0,"bawu_type":"","tshow_icon":[],"new_tshow_icon":[]},"sub_post_number":9,"add_post_number":0,"sub_post_list":[],"add_post_list":[]},{"id":"30943459645","title":"\u56de\u590d\uff1a\u76f4\u64ad\uff0cMC 1.3 \u539f\u7248\u751f\u5b58","floor":14798,"time":1364699850,"content":[{"type":0,"text":"\u597d\u5427\uff0c\u51b3\u5b9a\u4eca\u5929\u5c31\u73a9\u5230\u8fd9\u91cc\u4e86\n\u8fd9\u4e2a\u5de5\u7a0b\u8fd8\u6ca1\u5b8c\u5de5\uff0c\u6700\u91cd\u8981\u7684\u7535\u8def\u90e8\u5206\u8fd8\u6ca1\u505a\u5462\n1\u4e2a\u63a7\u5236\u662f\u5426\u7e41\u6b96\u7684\u7535\u8def\n\u548c2\u8fb9\u8fdb\u884c\u6751\u6c11\u5904\u7406\u7684\u7535\u8def\n\u4e0b\u4e00\u6b21\u76f4\u64ad\u65f6\u5c31\u505a\n \n\u2014\u2014\u6765\u81ea MCLive"},{"type":3,"src":"http:\/\/imgsrc.baidu.com\/forum\/pic\/item\/44d1e6fdfc039245d248c96f8694a4c27c1e25eb.jpg","bsize":"560,314","size":null}],"lbs_info":[],"is_vote":0,"ptype":null,"is_voice":0,"arr_video":[],"bimg_url":"","ios_bimg_format":"","is_bub":0,"has_signature":0,"pb_live":null,"signature":[],"vote_id":0,"tail_info":[],"author":{"id":105525655,"name":"defanive2","name_show":"defanive2","portrait":"9731646566616e697665324a06","type":1,"is_like":1,"level_id":14,"level_name":"\u65e0\u5c3d\u9ed1\u591c","is_interestman":"","iconinfo":[],"fans_nickname":"","is_mem":0,"tb_vip":[],"is_bawu":0,"bawu_type":"","tshow_icon":[],"new_tshow_icon":[]},"sub_post_number":7,"add_post_number":0,"sub_post_list":[],"add_post_list":[]},{"id":"30949529485","title":"\u56de\u590d\uff1a\u76f4\u64ad\uff0cMC 1.3 \u539f\u7248\u751f\u5b58","floor":14833,"time":1364711168,"content":[{"type":0,"text":"\u987a\u4fbf\u8865\u4e00\u4e0b\u56fe\u4e66\u7ba1\u7406\u5458\u4ea4\u6613\u7684\u4e00\u4e9b\u8be6\u60c5\n\u4ea4\u6613\u603b\u6570\uff1a9\u79cd\n24-35\u7eb8 -> 1\u7eff\u5b9d\u77f3\uff1a24.8%\n11-12\u4e66 -> 1\u7eff\u5b9d\u77f3\uff1a24.8%\n3\u7eff\u5b9d\u77f3 -> 1\u4e66\u67dc\uff1a24.8%\n1\u5199\u4e66 -> 1\u7eff\u5b9d\u77f3\uff1a7.9%\n1\u7eff\u5b9d\u77f3 -> 4-5\u73bb\u7483\uff1a5.2%\n10-11\u7eff\u5b9d\u77f3 -> 1\u65f6\u949f\uff1a5.2%\n10-11\u7eff\u5b9d\u77f3 -> 1\u6307\u5357\u9488\uff1a5.2%\n1\u4e66 + 5-71\u7eff\u5b9d\u77f3 -> \u9644\u9b54\u4e66\uff1a1.8%\n8-9\u91d1\u952d -> 1\u7eff\u5b9d\u77f3\uff1a0.3%"}],"lbs_info":[],"is_vote":0,"ptype":null,"is_voice":0,"arr_video":[],"bimg_url":"","ios_bimg_format":"","is_bub":0,"has_signature":0,"pb_live":null,"signature":[],"vote_id":0,"tail_info":[],"author":{"id":105525655,"name":"defanive2","name_show":"defanive2","portrait":"9731646566616e697665324a06","type":1,"is_like":1,"level_id":14,"level_name":"\u65e0\u5c3d\u9ed1\u591c","is_interestman":"","iconinfo":[],"fans_nickname":"","is_mem":0,"tb_vip":[],"is_bawu":0,"bawu_type":"","tshow_icon":[],"new_tshow_icon":[]},"sub_post_number":10,"add_post_number":0,"sub_post_list":[],"add_post_list":[]},{"id":"30949879755","title":"\u56de\u590d\uff1a\u76f4\u64ad\uff0cMC 1.3 \u539f\u7248\u751f\u5b58","floor":14835,"time":1364711881,"content":[{"type":0,"text":"\u987a\u4fbf\u8bf4\u4e00\u4e0b\u6211\u4e4b\u524d\u5237\u7684\u51e0\u4e2a\u56fe\u4e66\u7ba1\u7406\u5458\u7684\u8fc7\u7a0b\u548c\u6210\u679c\n\u4ee5\u4e0b\u5217\u51fa\u4e86\u56fe\u4e66\u7ba1\u7406\u5458\u7684\u4ea4\u6613\uff0c\u6309\u987a\u5e8f\u6392\u5217\uff0c\u4ee5\u53ca\u6700\u540e\u4ed6\u4eec\u7684\u7528\u5904\n#1\uff1a\u4e66\uff0c\u7eb8\uff1b\u4e22\u5f03\n#2\uff1a\u949f\uff0c\u7eb8\uff1b\u4e22\u5f03\n#3\uff1a\u73bb\u7483\uff0c\u7eb8\uff1b\u4e22\u5f03\n#4\uff1a\u4e66\u67b6\uff0c\u7eb8\uff1b\u4e22\u5f03\n#5\uff1a\u4e66\uff0c\u73bb\u7483\uff0c\u949f\uff0c\u6307\u5357\u9488\uff0c\u9644\u9b54\u4e66\uff0c\u5199\u4e66\uff0c\u7eb8\uff1b\u7eb8\u4ea4\u6613\u6e90\uff0c25%\u5e9f\u5f03\u7387\n#6\uff1a\u73bb\u7483\uff0c\u4e66\uff0c\u4e66\u67b6\uff0c\u949f\uff0c\u7eb8\uff1b\u4e22\u5f03\n#7\uff1a\u5199\u4e66\uff0c\u6307\u5357\u9488\uff0c\u949f\uff0c\u73bb\u7483\uff0c\u7eb8\uff0c\u4e66\u67b6\uff1b\u4e66\u67b6\u4ea4\u6613\u6e90\uff0c25%\u5e9f\u5f03\u7387\n#8\uff1a\u5199\u4e66\uff0c\u4e66\uff0c\u4e66\u67b6\uff0c\u6307\u5357\u9488\uff0c\u949f\uff0c\u7eb8\uff1b\u7eb8\u4ea4\u6613\u5458\uff0c7.1%\u5e9f\u5f03\u7387\n\u6700\u7ec8#5\u548c#8\u6210\u4e3a\u4e86\u7eb8\u4ea4\u6613\u7684\u6751\u6c11\uff0c\u53ef\u4ee5\u8fdb\u884c\uff08\u8fd1\uff09\u65e0\u9650\u6b21\u7eb8->\u7eff\u5b9d\u77f3\u4ea4\u6613\uff0c\u4ea4\u6613\u4ef7\u683c\u4e3a24\u548c26\u7eb8->1\u7eff\u5b9d\u77f3\n#7\u5219\u662f\u4e66\u67b6\u4ea4\u6613\u7684\u6751\u6c11\uff0c\u53ef\u4ee5\u8fdb\u884c\uff08\u8fd1\uff09\u65e0\u9650\u6b21\u4e66\u67b6\u4ea4\u6613\uff0c\u4ea4\u6613\u4ef7\u683c\u4e3a3\u7eff\u5b9d\u77f3->1\u4e66\u67b6\n\u63a5\u4e0b\u6765\u82e5#5\uff0c#7\uff0c#8\u5f00\u542f\u4e86\u6700\u540e\u4e00\u4e2a\u4ea4\u6613\u540e\uff0c\u4e5f\u5c31\u5e9f\u5f03\u4e86\uff1a\n#5\uff1a\u8f6c\u5316\u6210\u4e66\u67b6\u4ea4\u6613\u6e90\uff0c0.3%\u5e9f\u5f03\u7387\n#7\uff1a\u8f6c\u5316\u6210\u4e66\u4ea4\u6613\u6e90\uff0c5.4%\u5e9f\u5f03\u7387\uff0c\u53ef\u4ee5\u4e22\u5f03\n#8\uff1a\u8f6c\u5316\u6210\u73bb\u7483\u4ea4\u6613\u6e90\uff0c3.0%\u5e9f\u5f03\u7387"}],"lbs_info":[],"is_vote":0,"ptype":null,"is_voice":0,"arr_video":[],"bimg_url":"","ios_bimg_format":"","is_bub":0,"has_signature":0,"pb_live":null,"signature":[],"vote_id":0,"tail_info":[],"author":{"id":105525655,"name":"defanive2","name_show":"defanive2","portrait":"9731646566616e697665324a06","type":1,"is_like":1,"level_id":14,"level_name":"\u65e0\u5c3d\u9ed1\u591c","is_interestman":"","iconinfo":[],"fans_nickname":"","is_mem":0,"tb_vip":[],"is_bawu":0,"bawu_type":"","tshow_icon":[],"new_tshow_icon":[]},"sub_post_number":9,"add_post_number":0,"sub_post_list":[],"add_post_list":[]},{"id":"30949944618","title":"\u56de\u590d\uff1a\u76f4\u64ad\uff0cMC 1.3 \u539f\u7248\u751f\u5b58","floor":14836,"time":1364712011,"content":[{"type":0,"text":"\u603b\u4e4b\u7ed3\u8bba\u5c31\u662f\uff0c\u8fd9\u4e2a\u4ea4\u6613\u5de5\u7a0b\u662f\u5bf9\u4e00\u4e9b\u53ef\u518d\u751f\u7269\u8d44\u7684\u4e25\u5cfb\u8003\u9a8c\n\u5728\u5b8c\u6210\u52378\u4e2a\u6751\u6c11\u4e4b\u540e\uff0c\u4f7f\u7528\u4e86\u8fd11.5\u5927\u7bb1\u5b50\u7684\u7518\u8517\n\u4f46\u662f\u540c\u65f6\u4e5f\u8ba9\u7eff\u5b9d\u77f3\u53ef\u4ee5\u6709\u7a33\u5b9a\u7684\u6765\u6e90\u4e86\n\u4e5f\u5c31\u53ef\u4ee5\u8fdb\u884c\u4efb\u4f55\u4e00\u79cd\u5176\u4ed6\u7c7b\u578b\u7684\u6536\u8d2d\u4ea4\u6613\n\u5efa\u8bae\u540e\u671f\u53ef\u4ee5\u505a"}],"lbs_info":[],"is_vote":0,"ptype":null,"is_voice":0,"arr_video":[],"bimg_url":"","ios_bimg_format":"","is_bub":0,"has_signature":0,"pb_live":null,"signature":[],"vote_id":0,"tail_info":[],"author":{"id":105525655,"name":"defanive2","name_show":"defanive2","portrait":"9731646566616e697665324a06","type":1,"is_like":1,"level_id":14,"level_name":"\u65e0\u5c3d\u9ed1\u591c","is_interestman":"","iconinfo":[],"fans_nickname":"","is_mem":0,"tb_vip":[],"is_bawu":0,"bawu_type":"","tshow_icon":[],"new_tshow_icon":[]},"sub_post_number":10,"add_post_number":0,"sub_post_list":[],"add_post_list":[]},{"id":"30983113770","title":"\u56de\u590d\uff1a\u76f4\u64ad\uff0cMC 1.3 \u539f\u7248\u751f\u5b58","floor":14858,"time":1364791939,"content":[{"type":0,"text":"\u8bdd\u8bf4\u672c\u5e16\u7684\u56de\u590d\u6570\u5df2\u7ecf\u8d854W\u4e86\uff08\u5176\u5b9e\u6628\u5929\u76f4\u64ad\u524d\u5c31\u8d85\u4e86\uff09\n\u611f\u8c22\u5927\u5bb6\u7684\u652f\u6301\uff0c\u76f4\u64ad\u4ecd\u7136\u4f1a\u505a\u4e0b\u53bb\u7684\n\u5176\u5b9e\u8fd9\u4e2a\u76f4\u64ad\u4e5f\u5c31\u662f\u4e2a\u4eba\u73a9\u6e38\u620f\u7684\u8fc7\u7a0b\n\u53ea\u8981\u6211\u8fd8\u5728\u73a9MC\uff0c\u8fd8\u5728\u73a9\u8fd9\u4e2a\u4e16\u754c\uff0c\u5e94\u8be5\u5c31\u4e0d\u4f1a\u65ad\nPS \u8fc7\u4e00\u4f1a\u5c31\u53bb\u76f4\u64ad\u4e00\u4e0b\uff0c\u5148\u6d4b\u8bd5\u70b9\u4e1c\u897f"}],"lbs_info":[],"is_vote":0,"ptype":null,"is_voice":0,"arr_video":[],"bimg_url":"","ios_bimg_format":"","is_bub":0,"has_signature":0,"pb_live":null,"signature":[],"vote_id":0,"tail_info":[],"author":{"id":105525655,"name":"defanive2","name_show":"defanive2","portrait":"9731646566616e697665324a06","type":1,"is_like":1,"level_id":14,"level_name":"\u65e0\u5c3d\u9ed1\u591c","is_interestman":"","iconinfo":[],"fans_nickname":"","is_mem":0,"tb_vip":[],"is_bawu":0,"bawu_type":"","tshow_icon":[],"new_tshow_icon":[]},"sub_post_number":7,"add_post_number":0,"sub_post_list":[],"add_post_list":[]},{"id":"30984804982","title":"\u56de\u590d\uff1a\u76f4\u64ad\uff0cMC 1.3 \u539f\u7248\u751f\u5b58","floor":14866,"time":1364794761,"content":[{"type":0,"text":"\u4eca\u5929\u590d\u6d3b\u8282\uff0c\u73a9\u5b8c\u4e86\u6765\u7b80\u5355\u76f4\u64ad\u4e00\u4e0b\n\u4e4b\u524d\u88ab\u5f88\u591a\u4eba\u95ee\u4e86\u4e3a\u4ec0\u4e48\u4ec5\u4ec5\u51e0\u4e2a\u95e8\u5c31\u53ef\u4ee5\u65e0\u9650\u7e41\u6b96\n\u5148\u6765\u7b80\u5355\u8bb2\u89e3\u4e00\u4e0b\n\u9996\u5148\u88c5\u7f6e\u5f88\u7b80\u5355\uff0c\u4e0b\u65b9\u662f\u7e41\u6b96\u95f4\n\u4e0a\u65b96\u683c\u5904\u7ad9\u6709\u4e00\u4e2a\u6751\u6c11\uff0c\u4ee5\u53ca12\u9053\u95e8\n\u4e0b\u65b9\u7684\u6751\u6c11\u5c31\u4f1a\u65e0\u9650\u7684\u7e41\u6b96\u8d77\u6765\n \n\u2014\u2014\u6765\u81ea MCLive"},{"type":3,"src":"http:\/\/imgsrc.baidu.com\/forum\/pic\/item\/d9c0a8b1cb134954feaf2004574e9258d1094a39.jpg","bsize":"560,314","size":null}],"lbs_info":[],"is_vote":0,"ptype":null,"is_voice":0,"arr_video":[],"bimg_url":"","ios_bimg_format":"","is_bub":0,"has_signature":0,"pb_live":null,"signature":[],"vote_id":0,"tail_info":[],"author":{"id":105525655,"name":"defanive2","name_show":"defanive2","portrait":"9731646566616e697665324a06","type":1,"is_like":1,"level_id":14,"level_name":"\u65e0\u5c3d\u9ed1\u591c","is_interestman":"","iconinfo":[],"fans_nickname":"","is_mem":0,"tb_vip":[],"is_bawu":0,"bawu_type":"","tshow_icon":[],"new_tshow_icon":[]},"sub_post_number":62,"add_post_number":0,"sub_post_list":[],"add_post_list":[]},{"id":"30984896966","title":"\u56de\u590d\uff1a\u76f4\u64ad\uff0cMC 1.3 \u539f\u7248\u751f\u5b58","floor":14867,"time":1364794945,"content":[{"type":0,"text":"\u88c5\u7f6e\u4e0a\u65b9\u5f62\u6210\u4e86\u4e00\u4e2a\u6751\u5e84\uff1a\u6709\u81f3\u5c11\u4e00\u4e2a\u6751\u6c11\uff1b\u81f3\u5c11\u4e00\u4e2a\u7b26\u5408\u6761\u4ef6\u7684\u95e8\n\u6751\u5e84\u7684y\u503c\u68c0\u6d4b\u8303\u56f4\u53ea\u6709\u4e0d\u52305\u683c\uff0c\u56e0\u6b64\u68c0\u6d4b\u4e0d\u5230\u4e0b\u65b9\u7684\u6751\u6c11\n\u4e8e\u662f\u8fd9\u4e2a\u6751\u5e84\u5c31\u628a\u81ea\u5df1\u7684\u6751\u6c11\u6570\u91cf\u8bbe\u7f6e\u6210\u4e861\u4e2a\n\u867d\u7136\u4e0a\u65b9\u7684\u6751\u5e84\u610f\u8bc6\u4e0d\u5230\u4e0b\u65b9\u6709\u6751\u6c11\n\u4f46\u662f\u4e0b\u65b9\u7684\u6751\u6c11\u610f\u8bc6\u5230\u4e86\u4e0a\u65b9\u6709\u6751\u5e84\n\u800c\u4e0a\u65b9\u7684\u6751\u5e84\u670912\u9053\u7b26\u5408\u6761\u4ef6\u7684\u95e8\uff0c\u6bcf3\u9053\u95e8\u5c31\u53ef\u4ee5\u5bb9\u7eb31\u4e2a\u6751\u6c11\n\u56e0\u6b64\u4e0a\u65b9\u7684\u6751\u5e84\u53ef\u4ee5\u5bb9\u7eb34\u4e2a\u6751\u6c11\n\u4f46\u662f\u6751\u5e84\u7684\u4eba\u6570\u53ea\u67091\uff0c\u4e8e\u662f\u4e0b\u65b9\u7684\u6751\u6c11\u5c31\u5f00\u59cb\u7e41\u6b96\u4e86\n\u8fd9\u91cc\u662f\u5229\u7528\u7684\u6751\u5e84\u548c\u6751\u6c11\u68c0\u6d4b\u8303\u56f4\u7684\u4e0d\u5bf9\u79f0BUG\n \n\u2014\u2014\u6765\u81ea MCLive"},{"type":3,"src":"http:\/\/imgsrc.baidu.com\/forum\/pic\/item\/84247eb5c9ea15ce98d42b69b7003af33a87b2bc.jpg","bsize":"560,314","size":null}],"lbs_info":[],"is_vote":0,"ptype":null,"is_voice":0,"arr_video":[],"bimg_url":"","ios_bimg_format":"","is_bub":0,"has_signature":0,"pb_live":null,"signature":[],"vote_id":0,"tail_info":[],"author":{"id":105525655,"name":"defanive2","name_show":"defanive2","portrait":"9731646566616e697665324a06","type":1,"is_like":1,"level_id":14,"level_name":"\u65e0\u5c3d\u9ed1\u591c","is_interestman":"","iconinfo":[],"fans_nickname":"","is_mem":0,"tb_vip":[],"is_bawu":0,"bawu_type":"","tshow_icon":[],"new_tshow_icon":[]},"sub_post_number":17,"add_post_number":0,"sub_post_list":[],"add_post_list":[]}],"thread":{"id":"1766018024","reply_num":155364,"valid_post_num":9021,"repost_num":0,"thread_type":0,"comment_num":0,"isLzDeleteAll":0,"is_ad":0,"ecom":"","has_commented":0,"location":[],"is_ntitle":0,"is_bub":0,"create_time":1343886776,"collect_status":0,"collect_mark_pid":"0","title":"\u76f4\u64ad\uff0cMC 1.3 \u539f\u7248\u751f\u5b58","author":{"name":"defanive2","name_show":"defanive2","id":105525655,"type":1,"portrait":"9731646566616e697665324a06","level_id":14,"is_like":1,"is_verify":0,"iconinfo":[],"tshow_icon":[],"new_tshow_icon":[],"fans_nickname":"","tb_vip":[],"is_bawu":0,"bawu_type":"","has_concerned":0},"twzhibo_info":{"is_copytwzhibo":null,"user":{"tw_anchor_info":{"anchor_level":0,"in_black_list":0,"set_cover":0,"caller_msg":0,"follow":0,"guide":0,"newfloor":0,"fans_num":0,"month_update_days":0,"gifts_num":0}}},"pids":"30941245238,30941268218,30941295698,30941318039,30941329754,30941337431,30941353208,30941370089,30941391484,30941474106,30941499901,30941537240,30941544576,30941603579,30941621589,30941673844,30941694103,30941703664,30941720083,30941777998,30942036535,30942095762,30942554988,30943459645,30949529485,30949879755,30949944618,30983113770,30984804982,30984896966,","post_id":30941245238,"topic":{"is_topic":0,"topic_type":0,"is_live_post":0,"is_lpost":0,"lpost_type":0},"is_activity":"0"},"banner_list":{"app":[]},"server_time":172412,"time":1469774678,"ctime":0,"logid":2678260342,"error_code":"0"}