{"location":[],"has_floor":1,"is_new_url":0,"forum":{"id":2432903,"name":"minecraft","is_exists":1,"avatar":"http:\/\/imgsrc.baidu.com\/forum\/pic\/item\/9922720e0cf3d7cafaf3b171f71fbe096b63a9b4.jpg"},"add_post":{"last_addition_content":"\u5582\u718a","last_addition_time":"","post_id":22616303153,"create_time":1343886776,"already_count":0,"total_count":10,"warn_msg":"\u5427\u7b49\u7ea71\u7ea7\u4e4b\u4e0a\u53ef\u4ee5\u4f7f\u7528\u8ffd\u52a0\u529f\u80fd"},"user":{"is_login":0,"id":"","name":"","name_show":"","portrait":"","type":"","level_id":"","is_like":"","is_manager":"","bimg_url":"","pay_member_info":"","ios_bimg_format":"","bimg_end_time":"","is_mem":"","is_select_tail":""},"anti":{"tbs":"c6db3ec10a647e321469774623","ifvoice":1,"voice_message":"\u54ce\u5440\uff0c\u4e09\u7ea7\u4ee5\u4e0a\u624d\u80fd\u53d1\u8bed\u97f3\uff0c\u901f\u901f\u5347\u7ea7\u5427","video_message":"","ifaddition":0,"forbid_flag":1,"forbid_info":"\u672c\u5427\u76ee\u524d\u4ec5\u9650\u767b\u5f55\u7528\u6237\u53d1\u8d34","ifpost":0,"ifposta":0,"ifxiaoying":""},"page":{"req_num":30,"page_size":30,"offset":2310,"current_page":78,"total_page":301,"total_num":9030,"pnum":0,"tnum":0,"has_more":1,"has_prev":1},"post_list":[{"id":"23491921433","title":"\u56de\u590d\uff1a\u76f4\u64ad\uff0cMC 1.3 \u539f\u7248\u751f\u5b58","floor":4908,"time":1345799499,"content":[{"type":0,"text":"\u73b0\u5728\u8981\u53bb\u5e72\u4ec0\u4e48\u5462\uff1f\n\u5f88\u660e\u663e\u5e94\u8be5\u53bb\u6751\u5e84\u6362\u4e00\u4e9b\u94c1\u9550\u6765\u7528\nPS \u62d2\u7edd\u5237\u697c\uff01\u3002\u3002\u3002\u3002\n \n\u2014\u2014\u6765\u81ea MCLive"},{"type":3,"src":"http:\/\/imgsrc.baidu.com\/forum\/pic\/item\/c9fcc3cec3fdfc03d1a25f24d43f8794a5c22657.jpg","bsize":"560,314","size":null}],"lbs_info":[],"is_vote":0,"ptype":null,"is_voice":0,"arr_video":[],"bimg_url":"","ios_bimg_format":"","is_bub":0,"has_signature":0,"pb_live":null,"signature":[],"vote_id":0,"tail_info":[],"author":{"id":105525655,"name":"defanive2","name_show":"defanive2","portrait":"9731646566616e697665324a06","type":1,"is_like":1,"level_id":14,"level_name":"\u65e0\u5c3d\u9ed1\u591c","is_interestman":"","iconinfo":[],"fans_nickname":"","is_mem":0,"tb_vip":[],"is_bawu":0,"bawu_type":"","tshow_icon":[],"new_tshow_icon":[]},"sub_post_number":5,"add_post_number":0,"sub_post_list":[],"add_post_list":[]},{"id":"23492077934","title":"\u56de\u590d\uff1a\u76f4\u64ad\uff0cMC 1.3 \u539f\u7248\u751f\u5b58","floor":4911,"time":1345799755,"content":[{"type":0,"text":"\u957f\u9014\u8dcb\u6d89\u6765\u5230\u4e86\u6751\u5e84\n \n\u2014\u2014\u6765\u81ea MCLive"},{"type":3,"src":"http:\/\/imgsrc.baidu.com\/forum\/pic\/item\/eac4b74543a98226baad94bb8a82b9014a90eb3a.jpg","bsize":"560,314","size":null}],"lbs_info":[],"is_vote":0,"ptype":null,"is_voice":0,"arr_video":[],"bimg_url":"","ios_bimg_format":"","is_bub":0,"has_signature":0,"pb_live":null,"signature":[],"vote_id":0,"tail_info":[],"author":{"id":105525655,"name":"defanive2","name_show":"defanive2","portrait":"9731646566616e697665324a06","type":1,"is_like":1,"level_id":14,"level_name":"\u65e0\u5c3d\u9ed1\u591c","is_interestman":"","iconinfo":[],"fans_nickname":"","is_mem":0,"tb_vip":[],"is_bawu":0,"bawu_type":"","tshow_icon":[],"new_tshow_icon":[]},"sub_post_number":5,"add_post_number":0,"sub_post_list":[],"add_post_list":[]},{"id":"23492104975","title":"\u56de\u590d\uff1a\u76f4\u64ad\uff0cMC 1.3 \u539f\u7248\u751f\u5b58","floor":4912,"time":1345799799,"content":[{"type":0,"text":"\u5148\u628a\u4e00\u5806\u7eb8\u90fd\u6362\u6210\u7eff\u5b9d\u77f3\u5427\n \n\u2014\u2014\u6765\u81ea MCLive"},{"type":3,"src":"http:\/\/imgsrc.baidu.com\/forum\/pic\/item\/4afbfbedab64034f13a67d9aafc379310b551dc6.jpg","bsize":"560,314","size":null}],"lbs_info":[],"is_vote":0,"ptype":null,"is_voice":0,"arr_video":[],"bimg_url":"","ios_bimg_format":"","is_bub":0,"has_signature":0,"pb_live":null,"signature":[],"vote_id":0,"tail_info":[],"author":{"id":105525655,"name":"defanive2","name_show":"defanive2","portrait":"9731646566616e697665324a06","type":1,"is_like":1,"level_id":14,"level_name":"\u65e0\u5c3d\u9ed1\u591c","is_interestman":"","iconinfo":[],"fans_nickname":"","is_mem":0,"tb_vip":[],"is_bawu":0,"bawu_type":"","tshow_icon":[],"new_tshow_icon":[]},"sub_post_number":8,"add_post_number":0,"sub_post_list":[],"add_post_list":[]},{"id":"23492151733","title":"\u56de\u590d\uff1a\u76f4\u64ad\uff0cMC 1.3 \u539f\u7248\u751f\u5b58","floor":4913,"time":1345799875,"content":[{"type":0,"text":"\u8bdd\u8bf4\u94c1\u5320\u8fd8\u6709\u4e00\u4e2a\u7164\u6362\u7eff\u5b9d\u77f3\u7684\u4ea4\u6613\n\u672c\u6765\u60f3\u628a\u8fd9\u4e2a\u5237\u6389\u4f46\u662f\u6ca1\u5e26\u7164\u3002\u3002\n \n\u2014\u2014\u6765\u81ea MCLive"},{"type":3,"src":"http:\/\/imgsrc.baidu.com\/forum\/pic\/item\/bd3eb13533fa828b8094227ffd1f4134960a5af2.jpg","bsize":"560,314","size":null}],"lbs_info":[],"is_vote":0,"ptype":null,"is_voice":0,"arr_video":[],"bimg_url":"","ios_bimg_format":"","is_bub":0,"has_signature":0,"pb_live":null,"signature":[],"vote_id":0,"tail_info":[],"author":{"id":105525655,"name":"defanive2","name_show":"defanive2","portrait":"9731646566616e697665324a06","type":1,"is_like":1,"level_id":14,"level_name":"\u65e0\u5c3d\u9ed1\u591c","is_interestman":"","iconinfo":[],"fans_nickname":"","is_mem":0,"tb_vip":[],"is_bawu":0,"bawu_type":"","tshow_icon":[],"new_tshow_icon":[]},"sub_post_number":4,"add_post_number":0,"sub_post_list":[],"add_post_list":[]},{"id":"23492184565","title":"\u56de\u590d\uff1a\u76f4\u64ad\uff0cMC 1.3 \u539f\u7248\u751f\u5b58","floor":4914,"time":1345799929,"content":[{"type":0,"text":"\u4e8e\u662f\u6211\u51b3\u5b9a\u5230\u5929\u7136\u77ff\u9053\u6316\u70b9\u7164\n \n\u2014\u2014\u6765\u81ea MCLive"},{"type":3,"src":"http:\/\/imgsrc.baidu.com\/forum\/pic\/item\/d043ad4bd11373f0e6b1d003a40f4bfbfaed049b.jpg","bsize":"560,314","size":null}],"lbs_info":[],"is_vote":0,"ptype":null,"is_voice":0,"arr_video":[],"bimg_url":"","ios_bimg_format":"","is_bub":0,"has_signature":0,"pb_live":null,"signature":[],"vote_id":0,"tail_info":[],"author":{"id":105525655,"name":"defanive2","name_show":"defanive2","portrait":"9731646566616e697665324a06","type":1,"is_like":1,"level_id":14,"level_name":"\u65e0\u5c3d\u9ed1\u591c","is_interestman":"","iconinfo":[],"fans_nickname":"","is_mem":0,"tb_vip":[],"is_bawu":0,"bawu_type":"","tshow_icon":[],"new_tshow_icon":[]},"sub_post_number":5,"add_post_number":0,"sub_post_list":[],"add_post_list":[]},{"id":"23492221684","title":"\u56de\u590d\uff1a\u76f4\u64ad\uff0cMC 1.3 \u539f\u7248\u751f\u5b58","floor":4915,"time":1345799990,"content":[{"type":0,"text":"\u597d\u4e45\u6ca1\u53bb\u8fc7\u5929\u7136\u77ff\u6d1e\u63a2\u7d22\u4e86\n\u6316\u77ff\u7684\u8bdd\uff0c\u4e0d\u662f\u7ee7\u7eed\u7164\uff0c\u57fa\u672c\u4e0a\u4eba\u5de5\u77ff\u9053\u4ea7\u91cf\u5b8c\u7206\u5929\u7136\u77ff\u6d1e\n\u5c24\u5176\u662f\u94bb\u77f3\u7b49\u7269\uff0c\u51e0\u4e2a\u77ff\u9053\u5c31\u80fd\u6709\u4e00\u4e2a\u94bb\u77f3\u8109\n \n\u2014\u2014\u6765\u81ea MCLive"},{"type":3,"src":"http:\/\/imgsrc.baidu.com\/forum\/pic\/item\/08f790529822720eb93d5d667bcb0a46f31fabbf.jpg","bsize":"560,314","size":null}],"lbs_info":[],"is_vote":0,"ptype":null,"is_voice":0,"arr_video":[],"bimg_url":"","ios_bimg_format":"","is_bub":0,"has_signature":0,"pb_live":null,"signature":[],"vote_id":0,"tail_info":[],"author":{"id":105525655,"name":"defanive2","name_show":"defanive2","portrait":"9731646566616e697665324a06","type":1,"is_like":1,"level_id":14,"level_name":"\u65e0\u5c3d\u9ed1\u591c","is_interestman":"","iconinfo":[],"fans_nickname":"","is_mem":0,"tb_vip":[],"is_bawu":0,"bawu_type":"","tshow_icon":[],"new_tshow_icon":[]},"sub_post_number":13,"add_post_number":0,"sub_post_list":[],"add_post_list":[]},{"id":"23492537270","title":"\u56de\u590d\uff1a\u76f4\u64ad\uff0cMC 1.3 \u539f\u7248\u751f\u5b58","floor":4918,"time":1345800515,"content":[{"type":0,"text":"\u7b80\u5355\u6316\u4e8655\u4e2a\u7164\u77ff\uff0c\u53ef\u4ee5\u591f\u4ea4\u66133\u6b21\n\u4f46\u662f\u53ea\u4ea4\u6613\u5230\u628a\u4ea4\u6613\u5237\u6389\u5c31\u884c\u4e86\n \n\u2014\u2014\u6765\u81ea MCLive"},{"type":3,"src":"http:\/\/imgsrc.baidu.com\/forum\/pic\/item\/b90e7bec54e736d1d99c32949b504fc2d462699b.jpg","bsize":"560,314","size":null}],"lbs_info":[],"is_vote":0,"ptype":null,"is_voice":0,"arr_video":[],"bimg_url":"","ios_bimg_format":"","is_bub":0,"has_signature":0,"pb_live":null,"signature":[],"vote_id":0,"tail_info":[],"author":{"id":105525655,"name":"defanive2","name_show":"defanive2","portrait":"9731646566616e697665324a06","type":1,"is_like":1,"level_id":14,"level_name":"\u65e0\u5c3d\u9ed1\u591c","is_interestman":"","iconinfo":[],"fans_nickname":"","is_mem":0,"tb_vip":[],"is_bawu":0,"bawu_type":"","tshow_icon":[],"new_tshow_icon":[]},"sub_post_number":14,"add_post_number":0,"sub_post_list":[],"add_post_list":[]},{"id":"23492564549","title":"\u56de\u590d\uff1a\u76f4\u64ad\uff0cMC 1.3 \u539f\u7248\u751f\u5b58","floor":4919,"time":1345800561,"content":[{"type":0,"text":"\u8fd9\u91cc\u7684\u6751\u6c11\u5c31\u8fd9\u6837\u88ab\u65e0\u5f62\u7684\u7262\u7b3c\u56f0\u4f4f\u4e86\u3002\u3002\n \n\u2014\u2014\u6765\u81ea MCLive"},{"type":3,"src":"http:\/\/imgsrc.baidu.com\/forum\/pic\/item\/c995d143ad4bd113114a09ae5aafa40f4afb05a2.jpg","bsize":"560,314","size":null}],"lbs_info":[],"is_vote":0,"ptype":null,"is_voice":0,"arr_video":[],"bimg_url":"","ios_bimg_format":"","is_bub":0,"has_signature":0,"pb_live":null,"signature":[],"vote_id":0,"tail_info":[],"author":{"id":105525655,"name":"defanive2","name_show":"defanive2","portrait":"9731646566616e697665324a06","type":1,"is_like":1,"level_id":14,"level_name":"\u65e0\u5c3d\u9ed1\u591c","is_interestman":"","iconinfo":[],"fans_nickname":"","is_mem":0,"tb_vip":[],"is_bawu":0,"bawu_type":"","tshow_icon":[],"new_tshow_icon":[]},"sub_post_number":5,"add_post_number":0,"sub_post_list":[],"add_post_list":[]},{"id":"23492573413","title":"\u56de\u590d\uff1a\u76f4\u64ad\uff0cMC 1.3 \u539f\u7248\u751f\u5b58","floor":4920,"time":1345800576,"content":[{"type":0,"text":"\u6765\u6362\u4e00\u4e2a\n \n\u2014\u2014\u6765\u81ea MCLive"},{"type":3,"src":"http:\/\/imgsrc.baidu.com\/forum\/pic\/item\/aec379310a55b3199b7c3ce943a98226cefc17a0.jpg","bsize":"560,314","size":null}],"lbs_info":[],"is_vote":0,"ptype":null,"is_voice":0,"arr_video":[],"bimg_url":"","ios_bimg_format":"","is_bub":0,"has_signature":0,"pb_live":null,"signature":[],"vote_id":0,"tail_info":[],"author":{"id":105525655,"name":"defanive2","name_show":"defanive2","portrait":"9731646566616e697665324a06","type":1,"is_like":1,"level_id":14,"level_name":"\u65e0\u5c3d\u9ed1\u591c","is_interestman":"","iconinfo":[],"fans_nickname":"","is_mem":0,"tb_vip":[],"is_bawu":0,"bawu_type":"","tshow_icon":[],"new_tshow_icon":[]},"sub_post_number":5,"add_post_number":0,"sub_post_list":[],"add_post_list":[]},{"id":"23492584469","title":"\u56de\u590d\uff1a\u76f4\u64ad\uff0cMC 1.3 \u539f\u7248\u751f\u5b58","floor":4921,"time":1345800595,"content":[{"type":0,"text":"\u770b\u770b\u80fd\u51fa\u4ec0\u4e48\u597d\u7684\u4ea4\u6613\n \n\u2014\u2014\u6765\u81ea MCLive"},{"type":3,"src":"http:\/\/imgsrc.baidu.com\/forum\/pic\/item\/d000baa1cd11728b7cad32bec8fcc3cec2fd2cad.jpg","bsize":"560,314","size":null}],"lbs_info":[],"is_vote":0,"ptype":null,"is_voice":0,"arr_video":[],"bimg_url":"","ios_bimg_format":"","is_bub":0,"has_signature":0,"pb_live":null,"signature":[],"vote_id":0,"tail_info":[],"author":{"id":105525655,"name":"defanive2","name_show":"defanive2","portrait":"9731646566616e697665324a06","type":1,"is_like":1,"level_id":14,"level_name":"\u65e0\u5c3d\u9ed1\u591c","is_interestman":"","iconinfo":[],"fans_nickname":"","is_mem":0,"tb_vip":[],"is_bawu":0,"bawu_type":"","tshow_icon":[],"new_tshow_icon":[]},"sub_post_number":5,"add_post_number":0,"sub_post_list":[],"add_post_list":[]},{"id":"23492621854","title":"\u56de\u590d\uff1a\u76f4\u64ad\uff0cMC 1.3 \u539f\u7248\u751f\u5b58","floor":4922,"time":1345800658,"content":[{"type":0,"text":"\u597d\u50cf\u8fd9\u4e2a\u4ea4\u6613\u53d1\u8fbe\u4e86 = =\n\u7528\u94bb\u77f3\u7a3f\u6765\u6316\u77ff\u9e2d\u68a8\u4e0d\u5927\u554a\n \n\u2014\u2014\u6765\u81ea MCLive"},{"type":3,"src":"http:\/\/imgsrc.baidu.com\/forum\/pic\/item\/8326cffc1e178a82cee5c13cf603738da877e855.jpg","bsize":"560,314","size":null}],"lbs_info":[],"is_vote":0,"ptype":null,"is_voice":0,"arr_video":[],"bimg_url":"","ios_bimg_format":"","is_bub":0,"has_signature":0,"pb_live":null,"signature":[],"vote_id":0,"tail_info":[],"author":{"id":105525655,"name":"defanive2","name_show":"defanive2","portrait":"9731646566616e697665324a06","type":1,"is_like":1,"level_id":14,"level_name":"\u65e0\u5c3d\u9ed1\u591c","is_interestman":"","iconinfo":[],"fans_nickname":"","is_mem":0,"tb_vip":[],"is_bawu":0,"bawu_type":"","tshow_icon":[],"new_tshow_icon":[]},"sub_post_number":8,"add_post_number":0,"sub_post_list":[],"add_post_list":[]},{"id":"23492699631","title":"\u56de\u590d\uff1a\u76f4\u64ad\uff0cMC 1.3 \u539f\u7248\u751f\u5b58","floor":4923,"time":1345800791,"content":[{"type":0,"text":"\u75af\u72c2\u4ea4\u6613\u5237\u5230\u4e8639\u4e2a\u7eff\u5b9d\u77f3\u3002\u3002\n\u4f30\u8ba1\u8fd9\u4e2a\u4ea4\u6613\u8981\u5e9f\u6389\u4e86\u3002\u3002\nPS \u91cd\u65b0\u770b\u4e86\u4e00\u4e0bwiki\uff0c\u4ea4\u661313\u6b21\u6216\u8005\u4ee5\u4e0a\u5c31\u4f1a\u7acb\u5373\u79fb\u9664\n\u4ea4\u66133\u6b21\u6709\u79fb\u9664\u7684\u53ef\u80fd\n\u4f46\u662f\u6bcf\u6b21\u4e4b\u540e\u79fb\u9664\u6700\u540e\u4e00\u4e2a\u8fc713\u6b21\u7684\u4ea4\u6613\n\u5229\u7528\u8fd9\u4e2a\u53ef\u4ee5\u4fdd\u4f4f\u4e00\u4e9b\u91cd\u8981\u7684\u4ea4\u6613\n\u4f46\u662f\u6211\u8fd9\u91cc\u5176\u4ed6\u4ea4\u6613\u90fd\u4e0d\u600e\u4e48\u6837\u3002\u3002\n \n\u2014\u2014\u6765\u81ea MCLive"},{"type":3,"src":"http:\/\/imgsrc.baidu.com\/forum\/pic\/item\/c995d143ad4bd11312ef0eae5aafa40f4bfb050f.jpg","bsize":"560,314","size":null}],"lbs_info":[],"is_vote":0,"ptype":null,"is_voice":0,"arr_video":[],"bimg_url":"","ios_bimg_format":"","is_bub":0,"has_signature":0,"pb_live":null,"signature":[],"vote_id":0,"tail_info":[],"author":{"id":105525655,"name":"defanive2","name_show":"defanive2","portrait":"9731646566616e697665324a06","type":1,"is_like":1,"level_id":14,"level_name":"\u65e0\u5c3d\u9ed1\u591c","is_interestman":"","iconinfo":[],"fans_nickname":"","is_mem":0,"tb_vip":[],"is_bawu":0,"bawu_type":"","tshow_icon":[],"new_tshow_icon":[]},"sub_post_number":5,"add_post_number":0,"sub_post_list":[],"add_post_list":[]},{"id":"23492713685","title":"\u56de\u590d\uff1a\u76f4\u64ad\uff0cMC 1.3 \u539f\u7248\u751f\u5b58","floor":4924,"time":1345800816,"content":[{"type":0,"text":"\u7d2b\u8272\u5149\u5708\uff0c\u4f30\u8ba1\u90a3\u4e2a\u4ea4\u6613\u53c8\u7206\u6389\u4e86\n \n\u2014\u2014\u6765\u81ea MCLive"},{"type":3,"src":"http:\/\/imgsrc.baidu.com\/forum\/pic\/item\/f703738da9773912cf3a3cfdf8198618367ae20a.jpg","bsize":"560,314","size":null}],"lbs_info":[],"is_vote":0,"ptype":null,"is_voice":0,"arr_video":[],"bimg_url":"","ios_bimg_format":"","is_bub":0,"has_signature":0,"pb_live":null,"signature":[],"vote_id":0,"tail_info":[],"author":{"id":105525655,"name":"defanive2","name_show":"defanive2","portrait":"9731646566616e697665324a06","type":1,"is_like":1,"level_id":14,"level_name":"\u65e0\u5c3d\u9ed1\u591c","is_interestman":"","iconinfo":[],"fans_nickname":"","is_mem":0,"tb_vip":[],"is_bawu":0,"bawu_type":"","tshow_icon":[],"new_tshow_icon":[]},"sub_post_number":5,"add_post_number":0,"sub_post_list":[],"add_post_list":[]},{"id":"23492734992","title":"\u56de\u590d\uff1a\u76f4\u64ad\uff0cMC 1.3 \u539f\u7248\u751f\u5b58","floor":4925,"time":1345800852,"content":[{"type":0,"text":"\u6211\u4e86\u4e2a\u53bb\u53d8\u6210\u4e8624\u5f20\u7eb8\u63621\u4e2a\u7eff\u5b9d\u77f3\u3002\u3002\n\u53d1\u8fbe\u4e86\u7eff\u5b9d\u77f3\u53c8\u4e0d\u7528\u6101\u4e86\n \n\u2014\u2014\u6765\u81ea MCLive"},{"type":3,"src":"http:\/\/imgsrc.baidu.com\/forum\/pic\/item\/f31fbe096b63f624d044809f8744ebf81a4ca315.jpg","bsize":"560,314","size":null}],"lbs_info":[],"is_vote":0,"ptype":null,"is_voice":0,"arr_video":[],"bimg_url":"","ios_bimg_format":"","is_bub":0,"has_signature":0,"pb_live":null,"signature":[],"vote_id":0,"tail_info":[],"author":{"id":105525655,"name":"defanive2","name_show":"defanive2","portrait":"9731646566616e697665324a06","type":1,"is_like":1,"level_id":14,"level_name":"\u65e0\u5c3d\u9ed1\u591c","is_interestman":"","iconinfo":[],"fans_nickname":"","is_mem":0,"tb_vip":[],"is_bawu":0,"bawu_type":"","tshow_icon":[],"new_tshow_icon":[]},"sub_post_number":5,"add_post_number":0,"sub_post_list":[],"add_post_list":[]},{"id":"23492764513","title":"\u56de\u590d\uff1a\u76f4\u64ad\uff0cMC 1.3 \u539f\u7248\u751f\u5b58","floor":4926,"time":1345800903,"content":[{"type":0,"text":"\u4e8e\u662f39\u4e2a\u7eff\u5b9d\u77f3\u6362\u4e861\u4e2a\u94bb\u77f3\u7a3f\u548c4\u4e2a\u94c1\u9550\uff0c\u521a\u597d\u7528\u5b8c\n \n\u2014\u2014\u6765\u81ea MCLive"},{"type":3,"src":"http:\/\/imgsrc.baidu.com\/forum\/pic\/item\/b03533fa828ba61e8dfc71b34134970a304e591f.jpg","bsize":"560,314","size":null}],"lbs_info":[],"is_vote":0,"ptype":null,"is_voice":0,"arr_video":[],"bimg_url":"","ios_bimg_format":"","is_bub":0,"has_signature":0,"pb_live":null,"signature":[],"vote_id":0,"tail_info":[],"author":{"id":105525655,"name":"defanive2","name_show":"defanive2","portrait":"9731646566616e697665324a06","type":1,"is_like":1,"level_id":14,"level_name":"\u65e0\u5c3d\u9ed1\u591c","is_interestman":"","iconinfo":[],"fans_nickname":"","is_mem":0,"tb_vip":[],"is_bawu":0,"bawu_type":"","tshow_icon":[],"new_tshow_icon":[]},"sub_post_number":5,"add_post_number":0,"sub_post_list":[],"add_post_list":[]},{"id":"23492772801","title":"\u56de\u590d\uff1a\u76f4\u64ad\uff0cMC 1.3 \u539f\u7248\u751f\u5b58","floor":4927,"time":1345800918,"content":[{"type":0,"text":"\u770b\u770b\u53c8\u5237\u51fa\u4ec0\u4e48\u65b0\u4ea4\u6613\n \n\u2014\u2014\u6765\u81ea MCLive"},{"type":3,"src":"http:\/\/imgsrc.baidu.com\/forum\/pic\/item\/f636afc379310a55dd296768b74543a982261018.jpg","bsize":"560,314","size":null}],"lbs_info":[],"is_vote":0,"ptype":null,"is_voice":0,"arr_video":[],"bimg_url":"","ios_bimg_format":"","is_bub":0,"has_signature":0,"pb_live":null,"signature":[],"vote_id":0,"tail_info":[],"author":{"id":105525655,"name":"defanive2","name_show":"defanive2","portrait":"9731646566616e697665324a06","type":1,"is_like":1,"level_id":14,"level_name":"\u65e0\u5c3d\u9ed1\u591c","is_interestman":"","iconinfo":[],"fans_nickname":"","is_mem":0,"tb_vip":[],"is_bawu":0,"bawu_type":"","tshow_icon":[],"new_tshow_icon":[]},"sub_post_number":5,"add_post_number":0,"sub_post_list":[],"add_post_list":[]},{"id":"23492785221","title":"\u56de\u590d\uff1a\u76f4\u64ad\uff0cMC 1.3 \u539f\u7248\u751f\u5b58","floor":4928,"time":1345800939,"content":[{"type":0,"text":"\u3002\u3002\u3002\u6211\u8981\u600e\u4e48\u5410\u69fd\u8fd9\u4e2a\u4ea4\u6613\n \n\u2014\u2014\u6765\u81ea MCLive"},{"type":3,"src":"http:\/\/imgsrc.baidu.com\/forum\/pic\/item\/e824b899a9014c08fc5b91390a7b02087af4f4ce.jpg","bsize":"560,314","size":null}],"lbs_info":[],"is_vote":0,"ptype":null,"is_voice":0,"arr_video":[],"bimg_url":"","ios_bimg_format":"","is_bub":0,"has_signature":0,"pb_live":null,"signature":[],"vote_id":0,"tail_info":[],"author":{"id":105525655,"name":"defanive2","name_show":"defanive2","portrait":"9731646566616e697665324a06","type":1,"is_like":1,"level_id":14,"level_name":"\u65e0\u5c3d\u9ed1\u591c","is_interestman":"","iconinfo":[],"fans_nickname":"","is_mem":0,"tb_vip":[],"is_bawu":0,"bawu_type":"","tshow_icon":[],"new_tshow_icon":[]},"sub_post_number":13,"add_post_number":0,"sub_post_list":[],"add_post_list":[]},{"id":"23492820082","title":"\u56de\u590d\uff1a\u76f4\u64ad\uff0cMC 1.3 \u539f\u7248\u751f\u5b58","floor":4929,"time":1345800998,"content":[{"type":0,"text":"\u6253\u9053\u56de\u5e9c\uff0c\u51c6\u5907\u56de\u5bb6 = =\n \n\u2014\u2014\u6765\u81ea MCLive"},{"type":3,"src":"http:\/\/imgsrc.baidu.com\/forum\/pic\/item\/359b033b5bb5c9eadeacba7fd539b6003bf3b3cb.jpg","bsize":"560,314","size":null}],"lbs_info":[],"is_vote":0,"ptype":null,"is_voice":0,"arr_video":[],"bimg_url":"","ios_bimg_format":"","is_bub":0,"has_signature":0,"pb_live":null,"signature":[],"vote_id":0,"tail_info":[],"author":{"id":105525655,"name":"defanive2","name_show":"defanive2","portrait":"9731646566616e697665324a06","type":1,"is_like":1,"level_id":14,"level_name":"\u65e0\u5c3d\u9ed1\u591c","is_interestman":"","iconinfo":[],"fans_nickname":"","is_mem":0,"tb_vip":[],"is_bawu":0,"bawu_type":"","tshow_icon":[],"new_tshow_icon":[]},"sub_post_number":8,"add_post_number":0,"sub_post_list":[],"add_post_list":[]},{"id":"23492913944","title":"\u56de\u590d\uff1a\u76f4\u64ad\uff0cMC 1.3 \u539f\u7248\u751f\u5b58","floor":4931,"time":1345801160,"content":[{"type":0,"text":"\u53c8\u8def\u8fc7\u8fd9\u4e2a\u7834\u70c2\u7684\u5730\u65b9\u3002\u3002\n\u771f\u5fc3\u60f3\u628a\u5b83\u586b\u6389 = =\n \n\u2014\u2014\u6765\u81ea MCLive"},{"type":3,"src":"http:\/\/imgsrc.baidu.com\/forum\/pic\/item\/f2deb48f8c5494eef886b6852df5e0fe98257e81.jpg","bsize":"560,314","size":null}],"lbs_info":[],"is_vote":0,"ptype":null,"is_voice":0,"arr_video":[],"bimg_url":"","ios_bimg_format":"","is_bub":0,"has_signature":0,"pb_live":null,"signature":[],"vote_id":0,"tail_info":[],"author":{"id":105525655,"name":"defanive2","name_show":"defanive2","portrait":"9731646566616e697665324a06","type":1,"is_like":1,"level_id":14,"level_name":"\u65e0\u5c3d\u9ed1\u591c","is_interestman":"","iconinfo":[],"fans_nickname":"","is_mem":0,"tb_vip":[],"is_bawu":0,"bawu_type":"","tshow_icon":[],"new_tshow_icon":[]},"sub_post_number":5,"add_post_number":0,"sub_post_list":[],"add_post_list":[]},{"id":"23492939968","title":"\u56de\u590d\uff1a\u76f4\u64ad\uff0cMC 1.3 \u539f\u7248\u751f\u5b58","floor":4932,"time":1345801205,"content":[{"type":0,"text":"\u5feb\u5929\u9ed1\u4e86\uff0c\u4e0d\u8fc7\u6211\u8fd8\u662f\u8d76\u5feb\u8d76\u56de\u5bb6\u5427\u3002\u3002\n\u53cd\u6b63\u4e00\u70b9\u602a\u6ca1\u4ec0\u4e48\u5173\u7cfb\uff0c\u6211\u6709\u94c1\u5251\u548c\u94bb\u77f3\u5957\n \n\u2014\u2014\u6765\u81ea MCLive"},{"type":3,"src":"http:\/\/imgsrc.baidu.com\/forum\/pic\/item\/64380cd7912397dd7e8721985982b2b7d1a287b4.jpg","bsize":"560,314","size":null}],"lbs_info":[],"is_vote":0,"ptype":null,"is_voice":0,"arr_video":[],"bimg_url":"","ios_bimg_format":"","is_bub":0,"has_signature":0,"pb_live":null,"signature":[],"vote_id":0,"tail_info":[],"author":{"id":105525655,"name":"defanive2","name_show":"defanive2","portrait":"9731646566616e697665324a06","type":1,"is_like":1,"level_id":14,"level_name":"\u65e0\u5c3d\u9ed1\u591c","is_interestman":"","iconinfo":[],"fans_nickname":"","is_mem":0,"tb_vip":[],"is_bawu":0,"bawu_type":"","tshow_icon":[],"new_tshow_icon":[]},"sub_post_number":14,"add_post_number":0,"sub_post_list":[],"add_post_list":[]},{"id":"23492992861","title":"\u56de\u590d\uff1a\u76f4\u64ad\uff0cMC 1.3 \u539f\u7248\u751f\u5b58","floor":4933,"time":1345801297,"content":[{"type":0,"text":"\u5230\u5bb6\uff0c\u9e2d\u68a8\u4e0d\u5927\n \n\u2014\u2014\u6765\u81ea MCLive"},{"type":3,"src":"http:\/\/imgsrc.baidu.com\/forum\/pic\/item\/fc1f4134970a304e0fde1966d1c8a786c8175ca9.jpg","bsize":"560,314","size":null}],"lbs_info":[],"is_vote":0,"ptype":null,"is_voice":0,"arr_video":[],"bimg_url":"","ios_bimg_format":"","is_bub":0,"has_signature":0,"pb_live":null,"signature":[],"vote_id":0,"tail_info":[],"author":{"id":105525655,"name":"defanive2","name_show":"defanive2","portrait":"9731646566616e697665324a06","type":1,"is_like":1,"level_id":14,"level_name":"\u65e0\u5c3d\u9ed1\u591c","is_interestman":"","iconinfo":[],"fans_nickname":"","is_mem":0,"tb_vip":[],"is_bawu":0,"bawu_type":"","tshow_icon":[],"new_tshow_icon":[]},"sub_post_number":24,"add_post_number":0,"sub_post_list":[],"add_post_list":[]},{"id":"23493097638","title":"\u56de\u590d\uff1a\u76f4\u64ad\uff0cMC 1.3 \u539f\u7248\u751f\u5b58","floor":4935,"time":1345801477,"content":[{"type":0,"text":"\u6309\u7167\u539f\u5b9a\u8ba1\u5212\uff0c\u51fa\u53d1\u53bb\u9644\u9b54\n \n\u2014\u2014\u6765\u81ea MCLive"},{"type":3,"src":"http:\/\/imgsrc.baidu.com\/forum\/pic\/item\/500fd9f9d72a6059e60159862834349b033bba1d.jpg","bsize":"560,314","size":null}],"lbs_info":[],"is_vote":0,"ptype":null,"is_voice":0,"arr_video":[],"bimg_url":"","ios_bimg_format":"","is_bub":0,"has_signature":0,"pb_live":null,"signature":[],"vote_id":0,"tail_info":[],"author":{"id":105525655,"name":"defanive2","name_show":"defanive2","portrait":"9731646566616e697665324a06","type":1,"is_like":1,"level_id":14,"level_name":"\u65e0\u5c3d\u9ed1\u591c","is_interestman":"","iconinfo":[],"fans_nickname":"","is_mem":0,"tb_vip":[],"is_bawu":0,"bawu_type":"","tshow_icon":[],"new_tshow_icon":[]},"sub_post_number":5,"add_post_number":0,"sub_post_list":[],"add_post_list":[]},{"id":"23493192995","title":"\u56de\u590d\uff1a\u76f4\u64ad\uff0cMC 1.3 \u539f\u7248\u751f\u5b58","floor":4937,"time":1345801641,"content":[{"type":0,"text":"\u53c8\u6765\u5230\u86cb\u75bc\u7684\u5c0f\u9ed1\u5854\n \n\u2014\u2014\u6765\u81ea MCLive"},{"type":3,"src":"http:\/\/imgsrc.baidu.com\/forum\/pic\/item\/d62a6059252dd42aed67b937033b5bb5c8eab8c4.jpg","bsize":"560,314","size":null}],"lbs_info":[],"is_vote":0,"ptype":null,"is_voice":0,"arr_video":[],"bimg_url":"","ios_bimg_format":"","is_bub":0,"has_signature":0,"pb_live":null,"signature":[],"vote_id":0,"tail_info":[],"author":{"id":105525655,"name":"defanive2","name_show":"defanive2","portrait":"9731646566616e697665324a06","type":1,"is_like":1,"level_id":14,"level_name":"\u65e0\u5c3d\u9ed1\u591c","is_interestman":"","iconinfo":[],"fans_nickname":"","is_mem":0,"tb_vip":[],"is_bawu":0,"bawu_type":"","tshow_icon":[],"new_tshow_icon":[]},"sub_post_number":23,"add_post_number":0,"sub_post_list":[],"add_post_list":[]},{"id":"23493270567","title":"\u56de\u590d\uff1a\u76f4\u64ad\uff0cMC 1.3 \u539f\u7248\u751f\u5b58","floor":4938,"time":1345801774,"content":[{"type":0,"text":"\u5148\u9644\u9b54\u4e00\u4e2a\u94bb\u77f3\u7a3f\n \n\u2014\u2014\u6765\u81ea MCLive"},{"type":3,"src":"http:\/\/imgsrc.baidu.com\/forum\/pic\/item\/38dbb6fd5266d01659a526b4972bd40734fa35e9.jpg","bsize":"560,314","size":null}],"lbs_info":[],"is_vote":0,"ptype":null,"is_voice":0,"arr_video":[],"bimg_url":"","ios_bimg_format":"","is_bub":0,"has_signature":0,"pb_live":null,"signature":[],"vote_id":0,"tail_info":[],"author":{"id":105525655,"name":"defanive2","name_show":"defanive2","portrait":"9731646566616e697665324a06","type":1,"is_like":1,"level_id":14,"level_name":"\u65e0\u5c3d\u9ed1\u591c","is_interestman":"","iconinfo":[],"fans_nickname":"","is_mem":0,"tb_vip":[],"is_bawu":0,"bawu_type":"","tshow_icon":[],"new_tshow_icon":[]},"sub_post_number":5,"add_post_number":0,"sub_post_list":[],"add_post_list":[]},{"id":"23493281745","title":"\u56de\u590d\uff1a\u76f4\u64ad\uff0cMC 1.3 \u539f\u7248\u751f\u5b58","floor":4939,"time":1345801793,"content":[{"type":0,"text":"\u6548\u73874\u5509\uff0c\u597d\u50cf\u4e0d\u662f\u5f88\u503c\n \n\u2014\u2014\u6765\u81ea MCLive"},{"type":3,"src":"http:\/\/imgsrc.baidu.com\/forum\/pic\/item\/1b4c510fd9f9d72aa2dba881d42a2834359bbbeb.jpg","bsize":"560,314","size":null}],"lbs_info":[],"is_vote":0,"ptype":null,"is_voice":0,"arr_video":[],"bimg_url":"","ios_bimg_format":"","is_bub":0,"has_signature":0,"pb_live":null,"signature":[],"vote_id":0,"tail_info":[],"author":{"id":105525655,"name":"defanive2","name_show":"defanive2","portrait":"9731646566616e697665324a06","type":1,"is_like":1,"level_id":14,"level_name":"\u65e0\u5c3d\u9ed1\u591c","is_interestman":"","iconinfo":[],"fans_nickname":"","is_mem":0,"tb_vip":[],"is_bawu":0,"bawu_type":"","tshow_icon":[],"new_tshow_icon":[]},"sub_post_number":5,"add_post_number":0,"sub_post_list":[],"add_post_list":[]},{"id":"23493392110","title":"\u56de\u590d\uff1a\u76f4\u64ad\uff0cMC 1.3 \u539f\u7248\u751f\u5b58","floor":4940,"time":1345801981,"content":[{"type":0,"text":"\u6765\u9644\u9b54\u94c1\u9550\n \n\u2014\u2014\u6765\u81ea MCLive"},{"type":3,"src":"http:\/\/imgsrc.baidu.com\/forum\/pic\/item\/fd039245d688d43fc521296e7d1ed21b0ff43ba5.jpg","bsize":"560,314","size":null}],"lbs_info":[],"is_vote":0,"ptype":null,"is_voice":0,"arr_video":[],"bimg_url":"","ios_bimg_format":"","is_bub":0,"has_signature":0,"pb_live":null,"signature":[],"vote_id":0,"tail_info":[],"author":{"id":105525655,"name":"defanive2","name_show":"defanive2","portrait":"9731646566616e697665324a06","type":1,"is_like":1,"level_id":14,"level_name":"\u65e0\u5c3d\u9ed1\u591c","is_interestman":"","iconinfo":[],"fans_nickname":"","is_mem":0,"tb_vip":[],"is_bawu":0,"bawu_type":"","tshow_icon":[],"new_tshow_icon":[]},"sub_post_number":5,"add_post_number":0,"sub_post_list":[],"add_post_list":[]},{"id":"23493401852","title":"\u56de\u590d\uff1a\u76f4\u64ad\uff0cMC 1.3 \u539f\u7248\u751f\u5b58","floor":4941,"time":1345801998,"content":[{"type":0,"text":"\u8fd9\u4e2a\u53ef\u4ee5\u62ff\u6765\u6316\u94bb\u77f3\u4e86\n \n\u2014\u2014\u6765\u81ea MCLive"},{"type":3,"src":"http:\/\/imgsrc.baidu.com\/forum\/pic\/item\/63d0f703918fa0ecaa36dc91269759ee3c6ddbbd.jpg","bsize":"560,314","size":null}],"lbs_info":[],"is_vote":0,"ptype":null,"is_voice":0,"arr_video":[],"bimg_url":"","ios_bimg_format":"","is_bub":0,"has_signature":0,"pb_live":null,"signature":[],"vote_id":0,"tail_info":[],"author":{"id":105525655,"name":"defanive2","name_show":"defanive2","portrait":"9731646566616e697665324a06","type":1,"is_like":1,"level_id":14,"level_name":"\u65e0\u5c3d\u9ed1\u591c","is_interestman":"","iconinfo":[],"fans_nickname":"","is_mem":0,"tb_vip":[],"is_bawu":0,"bawu_type":"","tshow_icon":[],"new_tshow_icon":[]},"sub_post_number":5,"add_post_number":0,"sub_post_list":[],"add_post_list":[]},{"id":"23493495727","title":"\u56de\u590d\uff1a\u76f4\u64ad\uff0cMC 1.3 \u539f\u7248\u751f\u5b58","floor":4943,"time":1345802160,"content":[{"type":0,"text":"\u597d\u5427\u6211\u53c8\u591a\u4e00\u4e2asilk touch\u7a3f\u4e86\u3002\u3002\n\u6316\u77ff\u6ca1\u4ec0\u4e48\u7528\n \n\u2014\u2014\u6765\u81ea MCLive"},{"type":3,"src":"http:\/\/imgsrc.baidu.com\/forum\/pic\/item\/503d269759ee3d6df2073f5743166d224e4ade6d.jpg","bsize":"560,314","size":null}],"lbs_info":[],"is_vote":0,"ptype":null,"is_voice":0,"arr_video":[],"bimg_url":"","ios_bimg_format":"","is_bub":0,"has_signature":0,"pb_live":null,"signature":[],"vote_id":0,"tail_info":[],"author":{"id":105525655,"name":"defanive2","name_show":"defanive2","portrait":"9731646566616e697665324a06","type":1,"is_like":1,"level_id":14,"level_name":"\u65e0\u5c3d\u9ed1\u591c","is_interestman":"","iconinfo":[],"fans_nickname":"","is_mem":0,"tb_vip":[],"is_bawu":0,"bawu_type":"","tshow_icon":[],"new_tshow_icon":[]},"sub_post_number":6,"add_post_number":0,"sub_post_list":[],"add_post_list":[]},{"id":"23493611752","title":"\u56de\u590d\uff1a\u76f4\u64ad\uff0cMC 1.3 \u539f\u7248\u751f\u5b58","floor":4944,"time":1345802358,"content":[{"type":0,"text":"\u3002\u3002\u5c31\u4e0d\u80fd\u7ed9\u4e00\u4e2a\u6316\u77ff\u7528\u7684\u7a3f\u5b50\u4e48\n \n\u2014\u2014\u6765\u81ea MCLive"},{"type":3,"src":"http:\/\/imgsrc.baidu.com\/forum\/pic\/item\/9213b07eca806538d6851f8f97dda144ad34823b.jpg","bsize":"560,314","size":null}],"lbs_info":[],"is_vote":0,"ptype":null,"is_voice":0,"arr_video":[],"bimg_url":"","ios_bimg_format":"","is_bub":0,"has_signature":0,"pb_live":null,"signature":[],"vote_id":0,"tail_info":[],"author":{"id":105525655,"name":"defanive2","name_show":"defanive2","portrait":"9731646566616e697665324a06","type":1,"is_like":1,"level_id":14,"level_name":"\u65e0\u5c3d\u9ed1\u591c","is_interestman":"","iconinfo":[],"fans_nickname":"","is_mem":0,"tb_vip":[],"is_bawu":0,"bawu_type":"","tshow_icon":[],"new_tshow_icon":[]},"sub_post_number":5,"add_post_number":0,"sub_post_list":[],"add_post_list":[]},{"id":"23493745749","title":"\u56de\u590d\uff1a\u76f4\u64ad\uff0cMC 1.3 \u539f\u7248\u751f\u5b58","floor":4945,"time":1345802590,"content":[{"type":0,"text":"\u6700\u540e\u4e00\u4e2a\u7a3f\u5b50\uff0c\u7ec8\u4e8e\u9644\u9b54\u51fa\u6316\u77ff\u7528\u7684\u4e86\n \n\u2014\u2014\u6765\u81ea MCLive"},{"type":3,"src":"http:\/\/imgsrc.baidu.com\/forum\/pic\/item\/d62a6059252dd42aec49ba37033b5bb5c8eab8ee.jpg","bsize":"560,314","size":null}],"lbs_info":[],"is_vote":0,"ptype":null,"is_voice":0,"arr_video":[],"bimg_url":"","ios_bimg_format":"","is_bub":0,"has_signature":0,"pb_live":null,"signature":[],"vote_id":0,"tail_info":[],"author":{"id":105525655,"name":"defanive2","name_show":"defanive2","portrait":"9731646566616e697665324a06","type":1,"is_like":1,"level_id":14,"level_name":"\u65e0\u5c3d\u9ed1\u591c","is_interestman":"","iconinfo":[],"fans_nickname":"","is_mem":0,"tb_vip":[],"is_bawu":0,"bawu_type":"","tshow_icon":[],"new_tshow_icon":[]},"sub_post_number":6,"add_post_number":0,"sub_post_list":[],"add_post_list":[]}],"thread":{"id":"1766018024","reply_num":155364,"valid_post_num":9021,"repost_num":0,"thread_type":0,"comment_num":0,"isLzDeleteAll":0,"is_ad":0,"ecom":"","has_commented":0,"location":[],"is_ntitle":0,"is_bub":0,"create_time":1343886776,"collect_status":0,"collect_mark_pid":"0","title":"\u76f4\u64ad\uff0cMC 1.3 \u539f\u7248\u751f\u5b58","author":{"name":"defanive2","name_show":"defanive2","id":105525655,"type":1,"portrait":"9731646566616e697665324a06","level_id":14,"is_like":1,"is_verify":0,"iconinfo":[],"tshow_icon":[],"new_tshow_icon":[],"fans_nickname":"","tb_vip":[],"is_bawu":0,"bawu_type":"","has_concerned":0},"twzhibo_info":{"is_copytwzhibo":null,"user":{"tw_anchor_info":{"anchor_level":0,"in_black_list":0,"set_cover":0,"caller_msg":0,"follow":0,"guide":0,"newfloor":0,"fans_num":0,"month_update_days":0,"gifts_num":0}}},"pids":"23491921433,23492077934,23492104975,23492151733,23492184565,23492221684,23492537270,23492564549,23492573413,23492584469,23492621854,23492699631,23492713685,23492734992,23492764513,23492772801,23492785221,23492820082,23492913944,23492939968,23492992861,23493097638,23493192995,23493270567,23493281745,23493392110,23493401852,23493495727,23493611752,23493745749,","post_id":23491921433,"topic":{"is_topic":0,"topic_type":0,"is_live_post":0,"is_lpost":0,"lpost_type":0},"is_activity":"0"},"banner_list":{"app":[]},"server_time":126588,"time":1469774623,"ctime":0,"logid":2622977684,"error_code":"0"}